{"text": "OLIVIA DUBOIS\nolivia.dubois@orange.fr | +33 6 12 34 56 78 | Paris, France\n\nEXPERIENCE PROFESSIONNELLE\n\nBlockchain Developer \u2014 Ledger\nJan 2021 \u2013 Present | Paris, France\n- Developed smart contracts for DeFi protocols using Solidity.\n- Audited internal codebases for security vulnerabilities.\n- Integrated hardware wallet support into Web3 dApps.\n\nFull Stack Developer \u2014 Dassault Syst\u00e8mes\nSep 2018 \u2013 Dec 2020 | V\u00e9lizy-Villacoublay, France\n- Built 3D web viewers using WebGL and Three.js.\n- Maintained RESTful APIs in Node.js.\n\nFORMATION\nDipl\u00f4me d'Ing\u00e9nieur \u2014 \u00c9cole Polytechnique \u2014 2018\n\nCOMP\u00c9TENCES\nSolidity, Ethereum, Web3.js, JavaScript, TypeScript, Node.js, C++, Rust, Cryptography, Git", "output": "{\"personal_information\": {\"name\": \"OLIVIA DUBOIS\", \"email\": \"olivia.dubois@orange.fr\", \"phone\": \"+33 6 12 34 56 78\", \"location\": \"Paris, France\"}, \"skills\": [\"Solidity\", \"Ethereum\", \"Web3.js\", \"JavaScript\", \"TypeScript\", \"Node.js\", \"C++\", \"Rust\", \"Cryptography\", \"Git\"], \"work_experience\": [{\"employer\": \"Ledger\", \"job_title\": \"Blockchain Developer\", \"start_date\": \"Jan 2021\", \"end_date\": \"Present\", \"location\": \"Paris, France\"}, {\"employer\": \"Dassault Syst\u00e8mes\", \"job_title\": \"Full Stack Developer\", \"start_date\": \"Sep 2018\", \"end_date\": \"Dec 2020\", \"location\": \"V\u00e9lizy-Villacoublay, France\"}], \"education\": [{\"degree\": \"Dipl\u00f4me d'Ing\u00e9nieur\", \"institution\": \"\u00c9cole Polytechnique\", \"graduation_year\": \"2018\"}]}"}
{"text": "Resume of ALAN TURING (Just Kidding, Alan Smith)\nSydney, Australia | 0400 123 456 | a.smith@tech.au\n\nPROFESSIONAL HISTORY\n\nAtlassian (Sydney)\nSenior SRE | Feb 2021 - Present\n\nCanva (Sydney)\nDevOps Engineer | Jan 2018 - Jan 2021\n\nEDUCATION\nUNSW - Bachelor of Software Engineering (2017)\n\nTECHNICAL SKILLS\nGo, Java, AWS, Terraform, Kubernetes, Prometheus, Grafana", "output": "{\"personal_information\": {\"name\": \"Alan Smith\", \"email\": \"a.smith@tech.au\", \"phone\": \"0400 123 456\", \"location\": \"Sydney, Australia\"}, \"skills\": [\"Go\", \"Java\", \"AWS\", \"Terraform\", \"Kubernetes\", \"Prometheus\", \"Grafana\"], \"work_experience\": [{\"employer\": \"Atlassian\", \"job_title\": \"Senior SRE\", \"start_date\": \"Feb 2021\", \"end_date\": \"Present\", \"location\": \"Sydney\"}, {\"employer\": \"Canva\", \"job_title\": \"DevOps Engineer\", \"start_date\": \"Jan 2018\", \"end_date\": \"Jan 2021\", \"location\": \"Sydney\"}], \"education\": [{\"degree\": \"Bachelor of Software Engineering\", \"institution\": \"UNSW\", \"graduation_year\": \"2017\"}]}"}
{"text": "Kenji Sato\nkenji.sato@robotics.jp\n+81 80 1234 5678\nKyoto, Japan\n\nWork History\n\nRobotics Engineer \u2014 Kyoto Robotics\nApr 2019 \u2013 Present | Kyoto\n- Developing motion planning algorithms for industrial arms using ROS (Robot Operating System).\n- Integrating 3D vision sensors for bin picking applications.\n- Coding in C++ and Python.\n\nResearch Assistant \u2014 Kyoto University\nApr 2017 \u2013 Mar 2019 | Kyoto\n- Worked on SLAM algorithms for mobile robots.\n\nEducation\nMaster of Informatics \u2014 Kyoto University \u2014 2017\n\nSkills\nC++, Python, ROS/ROS2, OpenCV, PCL (Point Cloud Library), SLAM, MoveIt, Linux, Git", "output": "{\"personal_information\": {\"name\": \"Kenji Sato\", \"email\": \"kenji.sato@robotics.jp\", \"phone\": \"+81 80 1234 5678\", \"location\": \"Kyoto, Japan\"}, \"skills\": [\"C++\", \"Python\", \"ROS/ROS2\", \"OpenCV\", \"PCL (Point Cloud Library)\", \"SLAM\", \"MoveIt\", \"Linux\", \"Git\"], \"work_experience\": [{\"employer\": \"Kyoto Robotics\", \"job_title\": \"Robotics Engineer\", \"start_date\": \"Apr 2019\", \"end_date\": \"Present\", \"location\": \"Kyoto\"}, {\"employer\": \"Kyoto University\", \"job_title\": \"Research Assistant\", \"start_date\": \"Apr 2017\", \"end_date\": \"Mar 2019\", \"location\": \"Kyoto\"}], \"education\": [{\"degree\": \"Master of Informatics\", \"institution\": \"Kyoto University\", \"graduation_year\": \"2017\"}]}"}
{"text": "SARA AHMED\nDubai, UAE | +971 50 000 0000 | s.ahmed@tech.ae\n\nKEY COMPETENCIES: Java Spring Boot; Microservices; Oracle DB; Kafka; Redis; Azure DevOps\n\nPROFESSIONAL EXPERIENCE\n\nSenior Java Developer, Emirates NBD (Dubai)\n03/2019 \u2013 Present\n- Led migration of monolithic core banking system to microservices.\n\nJava Developer, Etisalat (Abu Dhabi)\n06/2015 \u2013 02/2019\n- Developed CRM modules.\n\nEDUCATION\nBSc Computer Engineering\nAmerican University of Sharjah (2015)", "output": "{\"personal_information\": {\"name\": \"SARA AHMED\", \"email\": \"s.ahmed@tech.ae\", \"phone\": \"+971 50 000 0000\", \"location\": \"Dubai, UAE\"}, \"skills\": [\"Java Spring Boot\", \"Microservices\", \"Oracle DB\", \"Kafka\", \"Redis\", \"Azure DevOps\"], \"work_experience\": [{\"employer\": \"Emirates NBD\", \"job_title\": \"Senior Java Developer\", \"start_date\": \"03/2019\", \"end_date\": \"Present\", \"location\": \"Dubai\"}, {\"employer\": \"Etisalat\", \"job_title\": \"Java Developer\", \"start_date\": \"06/2015\", \"end_date\": \"02/2019\", \"location\": \"Abu Dhabi\"}], \"education\": [{\"degree\": \"BSc Computer Engineering\", \"institution\": \"American University of Sharjah\", \"graduation_year\": \"2015\"}]}"}
{"text": "Finn Nielsen\nfinn.nielsen@tech.dk | +45 20 12 34 56 | Copenhagen, Denmark\n\nExperience\n\nSenior Software Engineer \u2014 Unity\nMar 2017 \u2013 Present | Copenhagen\n- Developing the core C++ runtime for Unity engine.\n- Optimizing memory allocation strategies for console platforms (PS5, Xbox).\n- Mentoring junior engine programmers.\n\nGame Programmer \u2014 IO Interactive\nAug 2013 \u2013 Feb 2017 | Copenhagen\n- Implemented AI behavior trees for the Hitman franchise.\n\nEducation\nMSc Computer Science \u2014 University of Copenhagen \u2014 2013\n\nSkills\nC++, C#, Game Development, Memory Management, Multithreading, HLSL, Python, Perforce, Visual Studio", "output": "{\"personal_information\": {\"name\": \"Finn Nielsen\", \"email\": \"finn.nielsen@tech.dk\", \"phone\": \"+45 20 12 34 56\", \"location\": \"Copenhagen, Denmark\"}, \"skills\": [\"C++\", \"C#\", \"Game Development\", \"Memory Management\", \"Multithreading\", \"HLSL\", \"Python\", \"Perforce\", \"Visual Studio\"], \"work_experience\": [{\"employer\": \"Unity\", \"job_title\": \"Senior Software Engineer\", \"start_date\": \"Mar 2017\", \"end_date\": \"Present\", \"location\": \"Copenhagen\"}, {\"employer\": \"IO Interactive\", \"job_title\": \"Game Programmer\", \"start_date\": \"Aug 2013\", \"end_date\": \"Feb 2017\", \"location\": \"Copenhagen\"}], \"education\": [{\"degree\": \"MSc Computer Science\", \"institution\": \"University of Copenhagen\", \"graduation_year\": \"2013\"}]}"}
{"text": "JULIA SANTOS\njulia.santos@email.pt\n+351 91 234 5678\nLisbon, Portugal\n\nExperience\n\nFull Stack Developer \u2014 Farfetch\nJul 2019 \u2013 Present | Lisbon, Portugal\n- Developing micro-frontends for the luxury fashion marketplace.\n- Implemented server-side rendering (SSR) strategies to improve SEO.\n- Integrating payment gateways (Adyen, PayPal).\n\nJunior Web Developer \u2014 Talkdesk\nSep 2017 \u2013 Jun 2019 | Lisbon, Portugal\n- Worked on real-time dashboard widgets using Vue.js.\n- Maintained Ruby on Rails backend services.\n\nEducation\nMSc Informatics Engineering \u2014 Instituto Superior T\u00e9cnico \u2014 2017\n\nSkills\nJavaScript, Vue.js, React, Node.js, C#, .NET Core, SQL Server, Ruby on Rails, Git, Docker", "output": "{\"personal_information\": {\"name\": \"JULIA SANTOS\", \"email\": \"julia.santos@email.pt\", \"phone\": \"+351 91 234 5678\", \"location\": \"Lisbon, Portugal\"}, \"skills\": [\"JavaScript\", \"Vue.js\", \"React\", \"Node.js\", \"C#\", \".NET Core\", \"SQL Server\", \"Ruby on Rails\", \"Git\", \"Docker\"], \"work_experience\": [{\"employer\": \"Farfetch\", \"job_title\": \"Full Stack Developer\", \"start_date\": \"Jul 2019\", \"end_date\": \"Present\", \"location\": \"Lisbon, Portugal\"}, {\"employer\": \"Talkdesk\", \"job_title\": \"Junior Web Developer\", \"start_date\": \"Sep 2017\", \"end_date\": \"Jun 2019\", \"location\": \"Lisbon, Portugal\"}], \"education\": [{\"degree\": \"MSc Informatics Engineering\", \"institution\": \"Instituto Superior T\u00e9cnico\", \"graduation_year\": \"2017\"}]}"}
{"text": "Anna Schmidt\nBerlin, DE | anna.s@web.de | +49 151 1234567\n\nBerufserfahrung:\n\nSAP Consultant @ Accenture (Munich)\nOct 2018 - Present\n\nJunior Developer @ SAP SE (Walldorf)\nSep 2015 - Sep 2018\n\nAusbildung:\nMSc Informatics, TU Munich, 2015\n\nKenntnisse:\nSAP ABAP, HANA, UI5, Fiori, Java, SQL, German, English", "output": "{\"personal_information\": {\"name\": \"Anna Schmidt\", \"email\": \"anna.s@web.de\", \"phone\": \"+49 151 1234567\", \"location\": \"Berlin, DE\"}, \"skills\": [\"SAP ABAP\", \"HANA\", \"UI5\", \"Fiori\", \"Java\", \"SQL\", \"German\", \"English\"], \"work_experience\": [{\"employer\": \"Accenture\", \"job_title\": \"SAP Consultant\", \"start_date\": \"Oct 2018\", \"end_date\": \"Present\", \"location\": \"Munich\"}, {\"employer\": \"SAP SE\", \"job_title\": \"Junior Developer\", \"start_date\": \"Sep 2015\", \"end_date\": \"Sep 2018\", \"location\": \"Walldorf\"}], \"education\": [{\"degree\": \"MSc Informatics\", \"institution\": \"TU Munich\", \"graduation_year\": \"2015\"}]}"}
{"text": "Yuki Tanaka\nyuki.tanaka@jp.sony.com\n+81 90-1234-5678\nTokyo, Japan\n\nCAREER HISTORY\n\nEmbedded Software Engineer | Sony Corporation\nApr 2018 \u2013 Present | Tokyo, Japan\n- Developed firmware for noise-canceling headphones using C/C++.\n- Optimized DSP algorithms for audio processing, reducing power consumption by 15%.\n- Collaborated with hardware teams for board bring-up and debugging.\n\nJunior Firmware Engineer | Toshiba\nApr 2015 \u2013 Mar 2018 | Kawasaki, Japan\n- Wrote drivers for SPI, I2C, and UART peripherals on ARM Cortex-M microcontrollers.\n\nEDUCATION\nMaster of Engineering \u2014 Tokyo Institute of Technology \u2014 2015\nBachelor of Engineering \u2014 Tokyo Institute of Technology \u2014 2013\n\nSKILLS\nC, C++, RTOS, ARM Cortex, Assembly, Python, Git, Oscilloscopes, Logic Analyzers, SPI/I2C", "output": "{\"personal_information\": {\"name\": \"Yuki Tanaka\", \"email\": \"yuki.tanaka@jp.sony.com\", \"phone\": \"+81 90-1234-5678\", \"location\": \"Tokyo, Japan\"}, \"skills\": [\"C\", \"C++\", \"RTOS\", \"ARM Cortex\", \"Assembly\", \"Python\", \"Git\", \"Oscilloscopes\", \"Logic Analyzers\", \"SPI/I2C\"], \"work_experience\": [{\"employer\": \"Sony Corporation\", \"job_title\": \"Embedded Software Engineer\", \"start_date\": \"Apr 2018\", \"end_date\": \"Present\", \"location\": \"Tokyo, Japan\"}, {\"employer\": \"Toshiba\", \"job_title\": \"Junior Firmware Engineer\", \"start_date\": \"Apr 2015\", \"end_date\": \"Mar 2018\", \"location\": \"Kawasaki, Japan\"}], \"education\": [{\"degree\": \"Master of Engineering\", \"institution\": \"Tokyo Institute of Technology\", \"graduation_year\": \"2015\"}, {\"degree\": \"Bachelor of Engineering\", \"institution\": \"Tokyo Institute of Technology\", \"graduation_year\": \"2013\"}]}"}
{"text": "Noa Cohen\nnoa.cohen@tech.il | +972 54 123 4567 | Tel Aviv, Israel\n\nExperience\n\nMLOps Engineer \u2014 Wiz\nJun 2021 \u2013 Present | Tel Aviv\n- Built end-to-end ML pipeline for anomaly detection using Kubeflow.\n- Managed model versioning and registry with MLflow.\n\nData Engineer \u2014 Check Point Software\nJan 2018 \u2013 May 2021 | Tel Aviv\n- Processed 10TB+ daily security logs using Apache Spark and Kafka.\n- Optimized Elasticsearch clusters for faster threat hunting.\n\nEducation\nBSc Computer Science \u2014 Technion - Israel Institute of Technology \u2014 2017\n\nSkills\nPython, Docker, Kubernetes, Kubeflow, MLflow, Apache Spark, Kafka, Elasticsearch, AWS, Jenkins", "output": "{\"personal_information\": {\"name\": \"Noa Cohen\", \"email\": \"noa.cohen@tech.il\", \"phone\": \"+972 54 123 4567\", \"location\": \"Tel Aviv, Israel\"}, \"skills\": [\"Python\", \"Docker\", \"Kubernetes\", \"Kubeflow\", \"MLflow\", \"Apache Spark\", \"Kafka\", \"Elasticsearch\", \"AWS\", \"Jenkins\"], \"work_experience\": [{\"employer\": \"Wiz\", \"job_title\": \"MLOps Engineer\", \"start_date\": \"Jun 2021\", \"end_date\": \"Present\", \"location\": \"Tel Aviv\"}, {\"employer\": \"Check Point Software\", \"job_title\": \"Data Engineer\", \"start_date\": \"Jan 2018\", \"end_date\": \"May 2021\", \"location\": \"Tel Aviv\"}], \"education\": [{\"degree\": \"BSc Computer Science\", \"institution\": \"Technion - Israel Institute of Technology\", \"graduation_year\": \"2017\"}]}"}
{"text": "Sophie Martin\nsophie.m@shopify-dev.ca | (647) 555-1234 | Toronto, ON, Canada\n\nEXPERIENCE\n\nShopify Developer \u2014 Agency X\nJan 2021 \u2013 Present | Toronto\n- Developing custom Shopify themes using Liquid and Tailwind CSS.\n- Building private apps using Node.js and Shopify GraphQL API.\n- Optimized store speed (Core Web Vitals) for enterprise clients.\n\nFrontend Developer \u2014 FreshBooks\nMar 2018 \u2013 Dec 2020 | Toronto\n- Worked on the marketing site using Ember.js and React.\n\nEDUCATION\nDiploma in Web Development \u2014 Humber College \u2014 2017\n\nSKILLS\nShopify, Liquid, JavaScript, React, Node.js, GraphQL, HTML/CSS, Git, Tailwind CSS", "output": "{\"personal_information\": {\"name\": \"Sophie Martin\", \"email\": \"sophie.m@shopify-dev.ca\", \"phone\": \"(647) 555-1234\", \"location\": \"Toronto, ON, Canada\"}, \"skills\": [\"Shopify\", \"Liquid\", \"JavaScript\", \"React\", \"Node.js\", \"GraphQL\", \"HTML/CSS\", \"Git\", \"Tailwind CSS\"], \"work_experience\": [{\"employer\": \"Agency X\", \"job_title\": \"Shopify Developer\", \"start_date\": \"Jan 2021\", \"end_date\": \"Present\", \"location\": \"Toronto\"}, {\"employer\": \"FreshBooks\", \"job_title\": \"Frontend Developer\", \"start_date\": \"Mar 2018\", \"end_date\": \"Dec 2020\", \"location\": \"Toronto\"}], \"education\": [{\"degree\": \"Diploma in Web Development\", \"institution\": \"Humber College\", \"graduation_year\": \"2017\"}]}"}
{"text": "Priya Singh\npriya.sfdc@gmail.com | +91 98111 22233 | Pune, India\n\nSummary\nSalesforce Certified Technical Architect with 7 years of ecosystem experience.\n\nProfessional Experience\n\nSalesforce Tech Lead \u2014 Deloitte Digital\nMay 2021 \u2013 Present | Pune\n- Designed custom Lightning Web Components (LWC) for manufacturing clients.\n- Orchestrated CI/CD pipelines using Salesforce DX and Copado.\n\nSenior Salesforce Developer \u2014 Tech Mahindra\nJun 2018 \u2013 Apr 2021 | Pune\n- Automated business processes using Apex Triggers and Flow Builder.\n- Integrated Salesforce with SAP ERP using Mulesoft.\n\nEducation\nB.E. Computer Science \u2014 Pune University \u2014 2018\n\nSkills\nApex, Visualforce, Lightning Web Components (LWC), Salesforce DX, SOQL, Copado, JavaScript, Mulesoft, Git", "output": "{\"personal_information\": {\"name\": \"Priya Singh\", \"email\": \"priya.sfdc@gmail.com\", \"phone\": \"+91 98111 22233\", \"location\": \"Pune, India\"}, \"skills\": [\"Apex\", \"Visualforce\", \"Lightning Web Components (LWC)\", \"Salesforce DX\", \"SOQL\", \"Copado\", \"JavaScript\", \"Mulesoft\", \"Git\"], \"work_experience\": [{\"employer\": \"Deloitte Digital\", \"job_title\": \"Salesforce Tech Lead\", \"start_date\": \"May 2021\", \"end_date\": \"Present\", \"location\": \"Pune\"}, {\"employer\": \"Tech Mahindra\", \"job_title\": \"Senior Salesforce Developer\", \"start_date\": \"Jun 2018\", \"end_date\": \"Apr 2021\", \"location\": \"Pune\"}], \"education\": [{\"degree\": \"B.E. Computer Science\", \"institution\": \"Pune University\", \"graduation_year\": \"2018\"}]}"}
{"text": "OBJECTIVE: To obtain a DevOps role.\n\nQUALIFICATIONS\n* 4 years with Kubernetes and Docker.\n* AWS Certified Solutions Architect.\n* Proficient in Terraform, Ansible, Go, Python.\n\nEMPLOYMENT\n\nDevOps Engineer | Shopify (Remote, Canada)\nJan 2020 - Present\nImplemented GitOps workflows using ArgoCD.\n\nSite Reliability Engineer | RBC (Toronto)\nMay 2017 - Dec 2019\nMaintained on-premise OpenShift cluster.\n\nEDUCATION\nUniversity of Waterloo, 2017\nBachelor of Computer Science\n\nCONTACT INFO\nDavid Miller\ndavid.m@devops.ca\n(647) 999-8888", "output": "{\"personal_information\": {\"name\": \"David Miller\", \"email\": \"david.m@devops.ca\", \"phone\": \"(647) 999-8888\", \"location\": \"Remote, Canada\"}, \"skills\": [\"Kubernetes\", \"Docker\", \"Terraform\", \"Ansible\", \"Go\", \"Python\", \"AWS Certified Solutions Architect\"], \"work_experience\": [{\"employer\": \"Shopify\", \"job_title\": \"DevOps Engineer\", \"start_date\": \"Jan 2020\", \"end_date\": \"Present\", \"location\": \"Remote, Canada\"}, {\"employer\": \"RBC\", \"job_title\": \"Site Reliability Engineer\", \"start_date\": \"May 2017\", \"end_date\": \"Dec 2019\", \"location\": \"Toronto\"}], \"education\": [{\"degree\": \"Bachelor of Computer Science\", \"institution\": \"University of Waterloo\", \"graduation_year\": \"2017\"}]}"}
{"text": "Chioma Okonkwo\nchioma.pm@tech.ng\n+234 803 123 4567\nLagos, Nigeria\n\nExperience\n\nSenior Product Manager \u2014 Paystack\nFeb 2021 \u2013 Present | Lagos\n- Led the launch of 'Pay with Transfer', processing $20M monthly volume.\n- Conducted user interviews and market research for expansion into Ghana.\n\nProduct Manager \u2014 Interswitch Group\nJan 2018 \u2013 Jan 2021 | Lagos\n- Managed API products for banking integration.\n- Collaborated with engineering to reduce transaction failure rates by 15%.\n\nEducation\nMSc Management Information Systems \u2014 Covenant University \u2014 2017\nBSc Computer Science \u2014 University of Lagos \u2014 2015\n\nSkills\nProduct Strategy, Roadmap Planning, SQL, Jira, Agile, User Research, API Design, Data Analysis, Stakeholder Management", "output": "{\"personal_information\": {\"name\": \"Chioma Okonkwo\", \"email\": \"chioma.pm@tech.ng\", \"phone\": \"+234 803 123 4567\", \"location\": \"Lagos, Nigeria\"}, \"skills\": [\"Product Strategy\", \"Roadmap Planning\", \"SQL\", \"Jira\", \"Agile\", \"User Research\", \"API Design\", \"Data Analysis\", \"Stakeholder Management\"], \"work_experience\": [{\"employer\": \"Paystack\", \"job_title\": \"Senior Product Manager\", \"start_date\": \"Feb 2021\", \"end_date\": \"Present\", \"location\": \"Lagos\"}, {\"employer\": \"Interswitch Group\", \"job_title\": \"Product Manager\", \"start_date\": \"Jan 2018\", \"end_date\": \"Jan 2021\", \"location\": \"Lagos\"}], \"education\": [{\"degree\": \"MSc Management Information Systems\", \"institution\": \"Covenant University\", \"graduation_year\": \"2017\"}, {\"degree\": \"BSc Computer Science\", \"institution\": \"University of Lagos\", \"graduation_year\": \"2015\"}]}"}
{"text": "Mark Mendoza\nmark.m@freelance.ph | +63 917 123 4567 | Manila, Philippines\n\nWork History\n\nSenior Web Developer \u2014 Upwork (Freelance)\nJan 2019 \u2013 Present | Manila\n- Developed custom WordPress themes and plugins for US-based clients.\n- Built e-commerce stores using WooCommerce and PHP.\n\nJunior Developer \u2014 Globe Telecom\nJun 2016 \u2013 Dec 2018 | Manila\n- Assisted in maintaining internal dashboard tools using jQuery and Bootstrap.\n\nEducation\nBS Computer Science \u2014 De La Salle University \u2014 2016\n\nSkills\nPHP, WordPress, WooCommerce, HTML5, CSS3, JavaScript, jQuery, MySQL, Bootstrap, Git", "output": "{\"personal_information\": {\"name\": \"Mark Mendoza\", \"email\": \"mark.m@freelance.ph\", \"phone\": \"+63 917 123 4567\", \"location\": \"Manila, Philippines\"}, \"skills\": [\"PHP\", \"WordPress\", \"WooCommerce\", \"HTML5\", \"CSS3\", \"JavaScript\", \"jQuery\", \"MySQL\", \"Bootstrap\", \"Git\"], \"work_experience\": [{\"employer\": \"Upwork (Freelance)\", \"job_title\": \"Senior Web Developer\", \"start_date\": \"Jan 2019\", \"end_date\": \"Present\", \"location\": \"Manila\"}, {\"employer\": \"Globe Telecom\", \"job_title\": \"Junior Developer\", \"start_date\": \"Jun 2016\", \"end_date\": \"Dec 2018\", \"location\": \"Manila\"}], \"education\": [{\"degree\": \"BS Computer Science\", \"institution\": \"De La Salle University\", \"graduation_year\": \"2016\"}]}"}
{"text": "Isabella Garcia\nisabella.g@outlook.es | +34 612 345 678 | Barcelona, Spain\n\nWORK EXPERIENCE\n\nData Engineer \u2014 Glovo | Sep 2021 \u2013 Present | Barcelona\n- Designed and maintained ETL pipelines processing 5TB+ daily data using Airflow and Spark.\n- Migrated data warehouse from Redshift to Snowflake, improving query performance by 2x.\n\nBig Data Developer \u2014 BBVA | Jul 2018 \u2013 Aug 2021 | Madrid\n- Developed streaming applications using Kafka Streams and Scala.\n- Built dashboards in Tableau for executive reporting.\n\nEDUCATION\nMSc Data Science \u2014 Universitat Polit\u00e8cnica de Catalunya \u2014 2018\nBSc Mathematics \u2014 Universidad Complutense de Madrid \u2014 2016\n\nSKILLS\nPython, Scala, SQL, Apache Spark, Airflow, Kafka, Snowflake, AWS, Docker, Terraform", "output": "{\"personal_information\": {\"name\": \"Isabella Garcia\", \"email\": \"isabella.g@outlook.es\", \"phone\": \"+34 612 345 678\", \"location\": \"Barcelona, Spain\"}, \"skills\": [\"Python\", \"Scala\", \"SQL\", \"Apache Spark\", \"Airflow\", \"Kafka\", \"Snowflake\", \"AWS\", \"Docker\", \"Terraform\"], \"work_experience\": [{\"employer\": \"Glovo\", \"job_title\": \"Data Engineer\", \"start_date\": \"Sep 2021\", \"end_date\": \"Present\", \"location\": \"Barcelona\"}, {\"employer\": \"BBVA\", \"job_title\": \"Big Data Developer\", \"start_date\": \"Jul 2018\", \"end_date\": \"Aug 2021\", \"location\": \"Madrid\"}], \"education\": [{\"degree\": \"MSc Data Science\", \"institution\": \"Universitat Polit\u00e8cnica de Catalunya\", \"graduation_year\": \"2018\"}, {\"degree\": \"BSc Mathematics\", \"institution\": \"Universidad Complutense de Madrid\", \"graduation_year\": \"2016\"}]}"}
{"text": "Oleg Kovalenko\noleg.qa@mail.ua\n+380 50 123 4567\nKyiv, Ukraine\n\nProfessional Experience\n\nLead QA Automation Engineer \u2014 Grammarly\nApr 2019 \u2013 Present | Kyiv\n- Architected test automation framework for browser extensions using Playwright.\n- Managed a team of 5 SDETs.\n\nQA Engineer \u2014 EPAM Systems\nNov 2015 \u2013 Mar 2019 | Kyiv\n- Automated REST API testing using Java and RestAssured.\n- Configured Jenkins pipelines for nightly regression runs.\n\nEducation\nSpecialist Degree in Computer Engineering \u2014 Kyiv Polytechnic Institute \u2014 2015\n\nSkills\nJava, TypeScript, Playwright, Selenium, Jenkins, Docker, REST API, SQL, Git, Allure", "output": "{\"personal_information\": {\"name\": \"Oleg Kovalenko\", \"email\": \"oleg.qa@mail.ua\", \"phone\": \"+380 50 123 4567\", \"location\": \"Kyiv, Ukraine\"}, \"skills\": [\"Java\", \"TypeScript\", \"Playwright\", \"Selenium\", \"Jenkins\", \"Docker\", \"REST API\", \"SQL\", \"Git\", \"Allure\"], \"work_experience\": [{\"employer\": \"Grammarly\", \"job_title\": \"Lead QA Automation Engineer\", \"start_date\": \"Apr 2019\", \"end_date\": \"Present\", \"location\": \"Kyiv\"}, {\"employer\": \"EPAM Systems\", \"job_title\": \"QA Engineer\", \"start_date\": \"Nov 2015\", \"end_date\": \"Mar 2019\", \"location\": \"Kyiv\"}], \"education\": [{\"degree\": \"Specialist Degree in Computer Engineering\", \"institution\": \"Kyiv Polytechnic Institute\", \"graduation_year\": \"2015\"}]}"}
{"text": "Arthur Dent\nadent@sysadmin.uk\n07700 900461\nLondon, UK\n\nProfile\nSystems Administrator with extensive experience in Linux and legacy Perl scripting.\n\nExperience\n\nSenior SysAdmin \u2014 BBC\nMay 2010 \u2013 Present | London\n- Managing 500+ RHEL servers for broadcast systems.\n- Maintaining legacy Perl automation scripts.\n- Configuring Apache web servers and Postfix mail relays.\n\nJunior Admin \u2014 British Airways\nJun 2005 \u2013 Apr 2010 | London\n- Support for Solaris UNIX environment.\n\nEducation\nHND Computing \u2014 London South Bank University \u2014 2005\n\nSkills\nLinux (RHEL/CentOS), Perl, Bash, Apache, Postfix, Nagios, Solaris, SSH, MySQL, Networking", "output": "{\"personal_information\": {\"name\": \"Arthur Dent\", \"email\": \"adent@sysadmin.uk\", \"phone\": \"07700 900461\", \"location\": \"London, UK\"}, \"skills\": [\"Linux (RHEL/CentOS)\", \"Perl\", \"Bash\", \"Apache\", \"Postfix\", \"Nagios\", \"Solaris\", \"SSH\", \"MySQL\", \"Networking\"], \"work_experience\": [{\"employer\": \"BBC\", \"job_title\": \"Senior SysAdmin\", \"start_date\": \"May 2010\", \"end_date\": \"Present\", \"location\": \"London\"}, {\"employer\": \"British Airways\", \"job_title\": \"Junior Admin\", \"start_date\": \"Jun 2005\", \"end_date\": \"Apr 2010\", \"location\": \"London\"}], \"education\": [{\"degree\": \"HND Computing\", \"institution\": \"London South Bank University\", \"graduation_year\": \"2005\"}]}"}
{"text": "Julia Rossi\njulia.r@email.it\nMilan, Italy\n\nFull Stack Dev.\n\nSkills: C#, .NET Core, Angular, SQL Server, Azure.\n\nExperience:\nReply (Milan) - .NET Consultant (2019-Present)\nAccenture (Rome) - Junior Analyst (2017-2019)\n\nEducation:\nPolitecnico di Milano, Master Comp Eng, 2017", "output": "{\"personal_information\": {\"name\": \"Julia Rossi\", \"email\": \"julia.r@email.it\", \"phone\": \"\", \"location\": \"Milan, Italy\"}, \"skills\": [\"C#\", \".NET Core\", \"Angular\", \"SQL Server\", \"Azure\"], \"work_experience\": [{\"employer\": \"Reply\", \"job_title\": \".NET Consultant\", \"start_date\": \"2019\", \"end_date\": \"Present\", \"location\": \"Milan\"}, {\"employer\": \"Accenture\", \"job_title\": \"Junior Analyst\", \"start_date\": \"2017\", \"end_date\": \"2019\", \"location\": \"Rome\"}], \"education\": [{\"degree\": \"Master Comp Eng\", \"institution\": \"Politecnico di Milano\", \"graduation_year\": \"2017\"}]}"}
{"text": "Dr. Eleanor Vance\ne.vance@genomics.ac.uk | +44 7700 900077 | Oxford, UK\n\nPROFESSIONAL SUMMARY\nBioinformatics Scientist with 6 years of experience in NGS data analysis and pipeline development.\n\nEXPERIENCE\nSenior Bioinformatician \u2014 Oxford Nanopore Technologies\nOct 2021 \u2013 Present | Oxford\n- Developed Nextflow pipelines for long-read sequencing data.\n- Optimized variant calling algorithms for structural variants.\n\nPostdoctoral Researcher \u2014 Wellcome Sanger Institute\nSep 2018 \u2013 Sep 2021 | Cambridge\n- Analyzed single-cell RNA-seq datasets for cancer immunology research.\n- Published 3 papers in Nature Genetics.\n\nEDUCATION\nPhD mainly Bioinformatics \u2014 University of Cambridge \u2014 2018\nBSc Genetics \u2014 University of Edinburgh \u2014 2014\n\nSKILLS\nPython, R, Nextflow, Docker, AWS, Linux, NGS, BLAST, Samtools, Git", "output": "{\"personal_information\": {\"name\": \"Dr. Eleanor Vance\", \"email\": \"e.vance@genomics.ac.uk\", \"phone\": \"+44 7700 900077\", \"location\": \"Oxford, UK\"}, \"skills\": [\"Python\", \"R\", \"Nextflow\", \"Docker\", \"AWS\", \"Linux\", \"NGS\", \"BLAST\", \"Samtools\", \"Git\"], \"work_experience\": [{\"employer\": \"Oxford Nanopore Technologies\", \"job_title\": \"Senior Bioinformatician\", \"start_date\": \"Oct 2021\", \"end_date\": \"Present\", \"location\": \"Oxford\"}, {\"employer\": \"Wellcome Sanger Institute\", \"job_title\": \"Postdoctoral Researcher\", \"start_date\": \"Sep 2018\", \"end_date\": \"Sep 2021\", \"location\": \"Cambridge\"}], \"education\": [{\"degree\": \"PhD mainly Bioinformatics\", \"institution\": \"University of Cambridge\", \"graduation_year\": \"2018\"}, {\"degree\": \"BSc Genetics\", \"institution\": \"University of Edinburgh\", \"graduation_year\": \"2014\"}]}"}
{"text": "SKILLS\nCybersecurity; SIEM (Splunk); Penetration Testing; Python; Linux; Network Security.\n\nEXPERIENCE\n\nSecurity Analyst II\nCrowdStrike - Remote\n2022-Present\n\nSOC Analyst\nFireEye - Milpitas, CA\n2019-2022\n\nEDUCATION\nBS InfoSec, Purdue University, 2019\n\nMichael Brown\nmichael.b@sec.io\n(202) 555-0101", "output": "{\"personal_information\": {\"name\": \"Michael Brown\", \"email\": \"michael.b@sec.io\", \"phone\": \"(202) 555-0101\", \"location\": \"Remote\"}, \"skills\": [\"Cybersecurity\", \"SIEM (Splunk)\", \"Penetration Testing\", \"Python\", \"Linux\", \"Network Security\"], \"work_experience\": [{\"employer\": \"CrowdStrike\", \"job_title\": \"Security Analyst II\", \"start_date\": \"2022\", \"end_date\": \"Present\", \"location\": \"Remote\"}, {\"employer\": \"FireEye\", \"job_title\": \"SOC Analyst\", \"start_date\": \"2019\", \"end_date\": \"2022\", \"location\": \"Milpitas, CA\"}], \"education\": [{\"degree\": \"BS InfoSec\", \"institution\": \"Purdue University\", \"graduation_year\": \"2019\"}]}"}
{"text": "Daniel Wright\ndwright22@gmail.com\n(512) 555-4321\nAustin, TX\n\nEmployment History\n\nGameplay Programmer \u2014 Bethesda Game Studios | Oct 2019 \u2013 Present | Austin, TX\nImplemented character movement and combat systems for AAA RPG title.\nOptimized physics engine interactions using C++ multi-threading.\n\nJunior Developer \u2014 Electronic Arts (EA) | Jul 2017 \u2013 Sep 2019 | Austin, TX\nWorked on UI/UX scripting for sports simulation games.\nDebugged crash reports and memory leaks in console builds.\n\nEducation\nBS Computer Science (Game Development) \u2014 University of Texas at Austin \u2014 2017\n\nSkills\nC++, C#, Unreal Engine 4/5, Unity, Lua, Perforce, Visual Studio, 3D Math, Physics Simulation", "output": "{\"personal_information\": {\"name\": \"Daniel Wright\", \"email\": \"dwright22@gmail.com\", \"phone\": \"(512) 555-4321\", \"location\": \"Austin, TX\"}, \"skills\": [\"C++\", \"C#\", \"Unreal Engine 4/5\", \"Unity\", \"Lua\", \"Perforce\", \"Visual Studio\", \"3D Math\", \"Physics Simulation\"], \"work_experience\": [{\"employer\": \"Bethesda Game Studios\", \"job_title\": \"Gameplay Programmer\", \"start_date\": \"Oct 2019\", \"end_date\": \"Present\", \"location\": \"Austin, TX\"}, {\"employer\": \"Electronic Arts (EA)\", \"job_title\": \"Junior Developer\", \"start_date\": \"Jul 2017\", \"end_date\": \"Sep 2019\", \"location\": \"Austin, TX\"}], \"education\": [{\"degree\": \"BS Computer Science (Game Development)\", \"institution\": \"University of Texas at Austin\", \"graduation_year\": \"2017\"}]}"}
{"text": "ALICE WALKER\nalicewalker@fastmail.fm\n+61 400 123 456\nSydney, Australia\n\nPROFESSIONAL EXPERIENCE\n\nSenior Frontend Developer \u2014 Canva\nFeb 2019 \u2013 Present | Sydney\n- Led the migration of legacy AngularJS code to React 18.\n- Improved editor load time by 40% using web workers and code splitting.\n- Developed accessibility standards (WCAG 2.1) adopted company-wide.\n\nWeb Developer \u2014 Atlassian\nJan 2016 \u2013 Jan 2019 | Sydney\n- Built reusable UI components for Jira Cloud using Atlaskit.\n- Collaborated with UX designers to implement new navigation patterns.\n\nEDUCATION\nBachelor of Information Technology \u2014 UTS \u2014 2015\n\nSKILLS\nReact, TypeScript, JavaScript, CSS3, HTML5, Webpack, Jest, Redux, GraphQL, Node.js", "output": "{\"personal_information\": {\"name\": \"ALICE WALKER\", \"email\": \"alicewalker@fastmail.fm\", \"phone\": \"+61 400 123 456\", \"location\": \"Sydney, Australia\"}, \"skills\": [\"React\", \"TypeScript\", \"JavaScript\", \"CSS3\", \"HTML5\", \"Webpack\", \"Jest\", \"Redux\", \"GraphQL\", \"Node.js\"], \"work_experience\": [{\"employer\": \"Canva\", \"job_title\": \"Senior Frontend Developer\", \"start_date\": \"Feb 2019\", \"end_date\": \"Present\", \"location\": \"Sydney\"}, {\"employer\": \"Atlassian\", \"job_title\": \"Web Developer\", \"start_date\": \"Jan 2016\", \"end_date\": \"Jan 2019\", \"location\": \"Sydney\"}], \"education\": [{\"degree\": \"Bachelor of Information Technology\", \"institution\": \"UTS\", \"graduation_year\": \"2015\"}]}"}
{"text": "Layla Al-Mansoori\nlayla.am@cyber.ae | +971 50 987 6543 | Abu Dhabi, UAE\n\nWork Experience\n\nSOC Analyst \u2014 DarkMatter\nJan 2020 \u2013 Present | Abu Dhabi\n- Investigating security incidents using Splunk and IBM QRadar.\n- Conducting threat hunting operations based on MITRE ATT&CK framework.\n- Automating incident response playbooks (SOAR).\n\nIT Security Intern \u2014 ADNO\nJun 2019 \u2013 Dec 2019 | Abu Dhabi\n- Assisted in firewall policy audits.\n\nEducation\nBSc Information Security \u2014 Zayed University \u2014 2019\n\nSkills\nSplunk, QRadar, Python, Incident Response, Threat Hunting, Malware Analysis, Wireshark, Linux, TCP/IP, MITRE ATT&CK", "output": "{\"personal_information\": {\"name\": \"Layla Al-Mansoori\", \"email\": \"layla.am@cyber.ae\", \"phone\": \"+971 50 987 6543\", \"location\": \"Abu Dhabi, UAE\"}, \"skills\": [\"Splunk\", \"QRadar\", \"Python\", \"Incident Response\", \"Threat Hunting\", \"Malware Analysis\", \"Wireshark\", \"Linux\", \"TCP/IP\", \"MITRE ATT&CK\"], \"work_experience\": [{\"employer\": \"DarkMatter\", \"job_title\": \"SOC Analyst\", \"start_date\": \"Jan 2020\", \"end_date\": \"Present\", \"location\": \"Abu Dhabi\"}, {\"employer\": \"ADNO\", \"job_title\": \"IT Security Intern\", \"start_date\": \"Jun 2019\", \"end_date\": \"Dec 2019\", \"location\": \"Abu Dhabi\"}], \"education\": [{\"degree\": \"BSc Information Security\", \"institution\": \"Zayed University\", \"graduation_year\": \"2019\"}]}"}
{"text": "MARCUS JOHNSON\nmarcus.j@devmail.com\n(404) 555-2233\nAtlanta, GA\n\nSUMMARY\nQA Automation Engineer with 5+ years experience building test frameworks.\n\nEXPERIENCE\n\nSDET III \u2014 The Home Depot\nMay 2021 \u2013 Present | Atlanta, GA\nBuilt hybrid test automation framework using Selenium and Cypress.\nIntegrated automated tests into Jenkins CI/CD pipeline, achieving 95% regression coverage.\n\nQA Engineer \u2014 Mailchimp\nJun 2018 \u2013 Apr 2021 | Atlanta, GA\nAutomated API testing using Postman and RestAssured.\nReduced manual testing effort by 60% within first year.\n\nEDUCATION\nBS Computer Science \u2014 Georgia Tech \u2014 2018\n\nSKILLS\nJava, JavaScript, Selenium WebDriver, Cypress, TestNG, JUnit, Jenkins, SQL, Postman, Git", "output": "{\"personal_information\": {\"name\": \"MARCUS JOHNSON\", \"email\": \"marcus.j@devmail.com\", \"phone\": \"(404) 555-2233\", \"location\": \"Atlanta, GA\"}, \"skills\": [\"Java\", \"JavaScript\", \"Selenium WebDriver\", \"Cypress\", \"TestNG\", \"JUnit\", \"Jenkins\", \"SQL\", \"Postman\", \"Git\"], \"work_experience\": [{\"employer\": \"The Home Depot\", \"job_title\": \"SDET III\", \"start_date\": \"May 2021\", \"end_date\": \"Present\", \"location\": \"Atlanta, GA\"}, {\"employer\": \"Mailchimp\", \"job_title\": \"QA Engineer\", \"start_date\": \"Jun 2018\", \"end_date\": \"Apr 2021\", \"location\": \"Atlanta, GA\"}], \"education\": [{\"degree\": \"BS Computer Science\", \"institution\": \"Georgia Tech\", \"graduation_year\": \"2018\"}]}"}
{"text": "Zoe Liu\nzoe.liu@startup.sg\nSingapore\n\nProduct Manager\n\nGrab (Singapore)\nProduct Lead - Payments\n2022 - Present\n\nShopee (Singapore)\nPM - Logistics\n2019 - 2022\n\nEducation:\nNUS (National Univ of Singapore)\nBBA, 2019\n\nSkills:\nProduct Management, Agile, SQL, Jira, Data Analysis, Stakeholder Mgmt", "output": "{\"personal_information\": {\"name\": \"Zoe Liu\", \"email\": \"zoe.liu@startup.sg\", \"phone\": \"\", \"location\": \"Singapore\"}, \"skills\": [\"Product Management\", \"Agile\", \"SQL\", \"Jira\", \"Data Analysis\", \"Stakeholder Mgmt\"], \"work_experience\": [{\"employer\": \"Grab\", \"job_title\": \"Product Lead - Payments\", \"start_date\": \"2022\", \"end_date\": \"Present\", \"location\": \"Singapore\"}, {\"employer\": \"Shopee\", \"job_title\": \"PM - Logistics\", \"start_date\": \"2019\", \"end_date\": \"2022\", \"location\": \"Singapore\"}], \"education\": [{\"degree\": \"BBA\", \"institution\": \"NUS\", \"graduation_year\": \"2019\"}]}"}
{"text": "Budi Santoso\nbudi.dev@gojek.com\n+62 812 3456 7890\nJakarta, Indonesia\n\nEXPERIENCE\n\nMobile Engineer (Flutter) \u2014 GoTo Group (Gojek)\nJan 2022 \u2013 Present | Jakarta\n- Migrated driver app modules from native Android to Flutter.\n- Implemented state management using Riverpod and BLoC pattern.\n\nAndroid Developer \u2014 Traveloka\nAug 2019 \u2013 Dec 2021 | Jakarta\n- Maintained flight booking features for 10M+ users.\n\nEDUCATION\nBachelor of Computer Science \u2014 University of Indonesia \u2014 2019\n\nSKILLS\nDart, Flutter, Android, Kotlin, Riverpod, Firebase, REST APIs, Git, Unit Testing, Figma", "output": "{\"personal_information\": {\"name\": \"Budi Santoso\", \"email\": \"budi.dev@gojek.com\", \"phone\": \"+62 812 3456 7890\", \"location\": \"Jakarta, Indonesia\"}, \"skills\": [\"Dart\", \"Flutter\", \"Android\", \"Kotlin\", \"Riverpod\", \"Firebase\", \"REST APIs\", \"Git\", \"Unit Testing\", \"Figma\"], \"work_experience\": [{\"employer\": \"GoTo Group (Gojek)\", \"job_title\": \"Mobile Engineer (Flutter)\", \"start_date\": \"Jan 2022\", \"end_date\": \"Present\", \"location\": \"Jakarta\"}, {\"employer\": \"Traveloka\", \"job_title\": \"Android Developer\", \"start_date\": \"Aug 2019\", \"end_date\": \"Dec 2021\", \"location\": \"Jakarta\"}], \"education\": [{\"degree\": \"Bachelor of Computer Science\", \"institution\": \"University of Indonesia\", \"graduation_year\": \"2019\"}]}"}
{"text": "Aisha Khan\naisha.khan@dev.pk\n+92 300 1234567\nLahore, Pakistan\n\nWork Experience\n\nFull Stack Developer (MERN) \u2014 Systems Limited\nOct 2020 \u2013 Present | Lahore\n- Developing enterprise web applications using MongoDB, Express, React, and Node.js.\n- Integrating third-party APIs (Stripe, Twilio).\n- Leading frontend architecture decisions.\n\nJunior Developer \u2014 Netsol Technologies\nJul 2018 \u2013 Sep 2020 | Lahore\n- Maintained legacy .NET applications.\n\nEducation\nBS Computer Science \u2014 LUMS \u2014 2018\n\nSkills\nJavaScript, React, Node.js, Express, MongoDB, Redux, HTML5, CSS3, Git, REST APIs", "output": "{\"personal_information\": {\"name\": \"Aisha Khan\", \"email\": \"aisha.khan@dev.pk\", \"phone\": \"+92 300 1234567\", \"location\": \"Lahore, Pakistan\"}, \"skills\": [\"JavaScript\", \"React\", \"Node.js\", \"Express\", \"MongoDB\", \"Redux\", \"HTML5\", \"CSS3\", \"Git\", \"REST APIs\"], \"work_experience\": [{\"employer\": \"Systems Limited\", \"job_title\": \"Full Stack Developer (MERN)\", \"start_date\": \"Oct 2020\", \"end_date\": \"Present\", \"location\": \"Lahore\"}, {\"employer\": \"Netsol Technologies\", \"job_title\": \"Junior Developer\", \"start_date\": \"Jul 2018\", \"end_date\": \"Sep 2020\", \"location\": \"Lahore\"}], \"education\": [{\"degree\": \"BS Computer Science\", \"institution\": \"LUMS\", \"graduation_year\": \"2018\"}]}"}
{"text": "JACK THOMPSON\njt.network@telco.au\n0412 345 678\nMelbourne, Australia\n\nEmployment\n\nNetwork Engineer \u2014 Telstra\nJul 2018 \u2013 Present | Melbourne\n- Managing core MPLS backbone network supporting 1M+ customers.\n- Configuring Juniper MX routers and Cisco Nexus switches.\n- Automating network configuration changes using Ansible and Python.\n\nNOC Technician \u2014 NBN Co\nJan 2016 \u2013 Jun 2018 | Melbourne\n- Monitored network alarms and performed L1 troubleshooting.\n\nEducation\nBachelor of Networking \u2014 RMIT University \u2014 2015\n\nSkills\nCisco IOS, Juniper Junos, BGP, OSPF, MPLS, Python, Ansible, Wireshark, Linux, Firewalls", "output": "{\"personal_information\": {\"name\": \"JACK THOMPSON\", \"email\": \"jt.network@telco.au\", \"phone\": \"0412 345 678\", \"location\": \"Melbourne, Australia\"}, \"skills\": [\"Cisco IOS\", \"Juniper Junos\", \"BGP\", \"OSPF\", \"MPLS\", \"Python\", \"Ansible\", \"Wireshark\", \"Linux\", \"Firewalls\"], \"work_experience\": [{\"employer\": \"Telstra\", \"job_title\": \"Network Engineer\", \"start_date\": \"Jul 2018\", \"end_date\": \"Present\", \"location\": \"Melbourne\"}, {\"employer\": \"NBN Co\", \"job_title\": \"NOC Technician\", \"start_date\": \"Jan 2016\", \"end_date\": \"Jun 2018\", \"location\": \"Melbourne\"}], \"education\": [{\"degree\": \"Bachelor of Networking\", \"institution\": \"RMIT University\", \"graduation_year\": \"2015\"}]}"}
{"text": "Ryan Lee\nryan.lee@techmail.sg\n+65 9123 4567\nSingapore\n\nWork Experience\n\nTech Lead \u2014 Grab\nMar 2020 \u2013 Present | Singapore\nLed the Superapp homepage team, managing 6 engineers.\nImproved app startup time by 30% through modular architecture.\n\nSenior Software Engineer \u2014 Sea Group (Shopee)\nJun 2016 \u2013 Feb 2020 | Singapore\nDeveloped high-traffic flash sale systems handling 50k QPS.\nOptimized Redis caching strategy to reduce database load.\n\nEducation\nB.Comp Computer Science \u2014 National University of Singapore (NUS) \u2014 2016\n\nSkills\nGo, Python, Java, Redis, MySQL, Kafka, Microservices, System Design, Kubernetes, GRPC", "output": "{\"personal_information\": {\"name\": \"Ryan Lee\", \"email\": \"ryan.lee@techmail.sg\", \"phone\": \"+65 9123 4567\", \"location\": \"Singapore\"}, \"skills\": [\"Go\", \"Python\", \"Java\", \"Redis\", \"MySQL\", \"Kafka\", \"Microservices\", \"System Design\", \"Kubernetes\", \"GRPC\"], \"work_experience\": [{\"employer\": \"Grab\", \"job_title\": \"Tech Lead\", \"start_date\": \"Mar 2020\", \"end_date\": \"Present\", \"location\": \"Singapore\"}, {\"employer\": \"Sea Group (Shopee)\", \"job_title\": \"Senior Software Engineer\", \"start_date\": \"Jun 2016\", \"end_date\": \"Feb 2020\", \"location\": \"Singapore\"}], \"education\": [{\"degree\": \"B.Comp Computer Science\", \"institution\": \"National University of Singapore (NUS)\", \"graduation_year\": \"2016\"}]}"}
{"text": "Ivan Petrov\nMoscow, Russia | +7 900 123 45 67 | ivan.p@yandex.ru\n\nBackend Developer (Go/Python)\n\nWORK EXPERIENCE\n\nAvito - Senior Go Developer\nMoscow | 2021 - Present\n\nYandex - Python Developer\nMoscow | 2018 - 2021\n\nEDUCATION\nBauman Moscow State Technical University\nSpecialist in Computer Security (2018)\n\nSKILLS\nGo, Python, PostgreSQL, Redis, Kafka, Docker, Kubernetes, gRPC", "output": "{\"personal_information\": {\"name\": \"Ivan Petrov\", \"email\": \"ivan.p@yandex.ru\", \"phone\": \"+7 900 123 45 67\", \"location\": \"Moscow, Russia\"}, \"skills\": [\"Go\", \"Python\", \"PostgreSQL\", \"Redis\", \"Kafka\", \"Docker\", \"Kubernetes\", \"gRPC\"], \"work_experience\": [{\"employer\": \"Avito\", \"job_title\": \"Senior Go Developer\", \"start_date\": \"2021\", \"end_date\": \"Present\", \"location\": \"Moscow\"}, {\"employer\": \"Yandex\", \"job_title\": \"Python Developer\", \"start_date\": \"2018\", \"end_date\": \"2021\", \"location\": \"Moscow\"}], \"education\": [{\"degree\": \"Specialist in Computer Security\", \"institution\": \"Bauman Moscow State Technical University\", \"graduation_year\": \"2018\"}]}"}
{"text": "Maria Gonzales\nUX/UI Designer based in Austin, Texas\nPortfolio: www.mariadesigns.com | Email: maria.g@design.co\n\nSummary: Passionate designer with 5 years exp.\n\nWork History:\n[2021-Present] Senior Designer @ Frog Design (Austin)\n- Leading design systems for fintech clients.\n\n[2018-2021] Product Designer @ IBM iX\n- User research and prototyping.\n\nEducation:\nBFA Interaction Design | SCAD | 2018\n\nTools:\nFigma, Sketch, Principle, Adobe CC, HTML/CSS, Zeplin", "output": "{\"personal_information\": {\"name\": \"Maria Gonzales\", \"email\": \"maria.g@design.co\", \"phone\": \"\", \"location\": \"Austin, Texas\"}, \"skills\": [\"Figma\", \"Sketch\", \"Principle\", \"Adobe CC\", \"HTML/CSS\", \"Zeplin\"], \"work_experience\": [{\"employer\": \"Frog Design\", \"job_title\": \"Senior Designer\", \"start_date\": \"2021\", \"end_date\": \"Present\", \"location\": \"Austin\"}, {\"employer\": \"IBM iX\", \"job_title\": \"Product Designer\", \"start_date\": \"2018\", \"end_date\": \"2021\", \"location\": \"\"}], \"education\": [{\"degree\": \"BFA Interaction Design\", \"institution\": \"SCAD\", \"graduation_year\": \"2018\"}]}"}
{"text": "Chen Wei\nchen.wei@qq.com | +86 138 0000 0000 | Shanghai, China\n\nExperience\n\nAlgorithm Engineer \u2014 ByteDance | Jul 2021 \u2013 Present | Shanghai\nOptimized recommendation algorithms for short-video platform using deep reinforcement learning.\nImproved user retention metrics by 0.5% through multi-objective optimization.\n\nMachine Learning Intern \u2014 Alibaba Group | May 2020 \u2013 Aug 2020 | Hangzhou\nResearched graph neural networks for fraud detection in e-commerce transactions.\n\nEducation\nM.S. Computer Science \u2014 Fudan University \u2014 2021\nB.S. Software Engineering \u2014 Shanghai Jiao Tong University \u2014 2018\n\nSkills\nPython, TensorFlow, PyTorch, C++, Hadoop, Spark, Scikit-learn, Deep Learning, NLP", "output": "{\"personal_information\": {\"name\": \"Chen Wei\", \"email\": \"chen.wei@qq.com\", \"phone\": \"+86 138 0000 0000\", \"location\": \"Shanghai, China\"}, \"skills\": [\"Python\", \"TensorFlow\", \"PyTorch\", \"C++\", \"Hadoop\", \"Spark\", \"Scikit-learn\", \"Deep Learning\", \"NLP\"], \"work_experience\": [{\"employer\": \"ByteDance\", \"job_title\": \"Algorithm Engineer\", \"start_date\": \"Jul 2021\", \"end_date\": \"Present\", \"location\": \"Shanghai\"}, {\"employer\": \"Alibaba Group\", \"job_title\": \"Machine Learning Intern\", \"start_date\": \"May 2020\", \"end_date\": \"Aug 2020\", \"location\": \"Hangzhou\"}], \"education\": [{\"degree\": \"M.S. Computer Science\", \"institution\": \"Fudan University\", \"graduation_year\": \"2021\"}, {\"degree\": \"B.S. Software Engineering\", \"institution\": \"Shanghai Jiao Tong University\", \"graduation_year\": \"2018\"}]}"}
{"text": "Sofia Costa\nsofia.c@tech.br\n(21) 98765-4321\nRio de Janeiro, Brazil\n\nExperience\n\nBackend Engineer (Golang) \u2014 Stone\nSep 2020 \u2013 Present | Rio de Janeiro\n- Building high-throughput payment processing microservices in Go.\n- Implemented gRPC communication between internal services.\n- Tuned PostgreSQL queries for 1TB+ datasets.\n\nPHP Developer \u2014 Localiza\nMar 2017 \u2013 Aug 2020 | Belo Horizonte\n- Maintained legacy monolithic application using Laravel.\n\nEducation\nTechnologist in Systems Analysis \u2014 PUC-Rio \u2014 2016\n\nSkills\nGo (Golang), PHP, PostgreSQL, Docker, Kubernetes, gRPC, Kafka, Redis, AWS, Git", "output": "{\"personal_information\": {\"name\": \"Sofia Costa\", \"email\": \"sofia.c@tech.br\", \"phone\": \"(21) 98765-4321\", \"location\": \"Rio de Janeiro, Brazil\"}, \"skills\": [\"Go (Golang)\", \"PHP\", \"PostgreSQL\", \"Docker\", \"Kubernetes\", \"gRPC\", \"Kafka\", \"Redis\", \"AWS\", \"Git\"], \"work_experience\": [{\"employer\": \"Stone\", \"job_title\": \"Backend Engineer (Golang)\", \"start_date\": \"Sep 2020\", \"end_date\": \"Present\", \"location\": \"Rio de Janeiro\"}, {\"employer\": \"Localiza\", \"job_title\": \"PHP Developer\", \"start_date\": \"Mar 2017\", \"end_date\": \"Aug 2020\", \"location\": \"Belo Horizonte\"}], \"education\": [{\"degree\": \"Technologist in Systems Analysis\", \"institution\": \"PUC-Rio\", \"graduation_year\": \"2016\"}]}"}
{"text": "Emily White\nLondon, UK\n\nExperience\n\nRevolut / Product Owner\nLondon / Jan 2021 - Present\n\nMonzo / Business Analyst\nLondon / Mar 2018 - Dec 2020\n\nEducation\nLSE / MSc Finance / 2017\nUCL / BSc Economics / 2016\n\nSkills\nAgile, SQL, Python, Jira, Product Strategy, Fintech\n\nContact: emily.w@fintech.uk / +44 7700 900000", "output": "{\"personal_information\": {\"name\": \"Emily White\", \"email\": \"emily.w@fintech.uk\", \"phone\": \"+44 7700 900000\", \"location\": \"London, UK\"}, \"skills\": [\"Agile\", \"SQL\", \"Python\", \"Jira\", \"Product Strategy\", \"Fintech\"], \"work_experience\": [{\"employer\": \"Revolut\", \"job_title\": \"Product Owner\", \"start_date\": \"Jan 2021\", \"end_date\": \"Present\", \"location\": \"London\"}, {\"employer\": \"Monzo\", \"job_title\": \"Business Analyst\", \"start_date\": \"Mar 2018\", \"end_date\": \"Dec 2020\", \"location\": \"London\"}], \"education\": [{\"degree\": \"MSc Finance\", \"institution\": \"LSE\", \"graduation_year\": \"2017\"}, {\"degree\": \"BSc Economics\", \"institution\": \"UCL\", \"graduation_year\": \"2016\"}]}"}
{"text": "JONATHAN PIERCE\nj.pierce@quantmail.com\n(212) 555-0011\nNew York, NY\n\nExperience\n\nQuantitative Developer \u2014 Citadel Securities\nMar 2022 \u2013 Present | New York, NY\n- optimizing low-latency trading execution strategies in C++20.\n- Reduced tick-to-trade latency by 15 microseconds via kernel bypass networking.\n\nSoftware Engineer \u2014 Bloomberg LP\nAug 2019 \u2013 Feb 2022 | New York, NY\n- Built real-time market data feed handlers processing 5M+ messages/sec.\n\nEducation\nMS Computational Finance \u2014 Carnegie Mellon University \u2014 2019\nBS Mathematics \u2014 MIT \u2014 2018\n\nSkills\nC++, C++17/20, Python, Linux, Multithreading, Kernel Bypass, TCP/IP, Boost, CMake, SQL", "output": "{\"personal_information\": {\"name\": \"JONATHAN PIERCE\", \"email\": \"j.pierce@quantmail.com\", \"phone\": \"(212) 555-0011\", \"location\": \"New York, NY\"}, \"skills\": [\"C++\", \"C++17/20\", \"Python\", \"Linux\", \"Multithreading\", \"Kernel Bypass\", \"TCP/IP\", \"Boost\", \"CMake\", \"SQL\"], \"work_experience\": [{\"employer\": \"Citadel Securities\", \"job_title\": \"Quantitative Developer\", \"start_date\": \"Mar 2022\", \"end_date\": \"Present\", \"location\": \"New York, NY\"}, {\"employer\": \"Bloomberg LP\", \"job_title\": \"Software Engineer\", \"start_date\": \"Aug 2019\", \"end_date\": \"Feb 2022\", \"location\": \"New York, NY\"}], \"education\": [{\"degree\": \"MS Computational Finance\", \"institution\": \"Carnegie Mellon University\", \"graduation_year\": \"2019\"}, {\"degree\": \"BS Mathematics\", \"institution\": \"MIT\", \"graduation_year\": \"2018\"}]}"}
{"text": "Lucas Oliveira\nS\u00e3o Paulo, SP\n(11) 98765-4321 / lucas.o@br.com\n\nExperience\n\nMercado Livre - Data Scientist\n2021 to Now\nFocus on fraud detection models using XGBoost and LightGBM.\n\nIta\u00fa Unibanco - Data Analyst\n2018 to 2021\nSQL queries and dashboards in Tableau.\n\nAcademic\nUSP (University of S\u00e3o Paulo) - Statistics (BS), 2018\n\nTech Stack\nPython, SQL, Spark, Pandas, Scikit-learn, Tableau, Airflow", "output": "{\"personal_information\": {\"name\": \"Lucas Oliveira\", \"email\": \"lucas.o@br.com\", \"phone\": \"(11) 98765-4321\", \"location\": \"S\u00e3o Paulo, SP\"}, \"skills\": [\"Python\", \"SQL\", \"Spark\", \"Pandas\", \"Scikit-learn\", \"Tableau\", \"Airflow\"], \"work_experience\": [{\"employer\": \"Mercado Livre\", \"job_title\": \"Data Scientist\", \"start_date\": \"2021\", \"end_date\": \"Now\", \"location\": \"S\u00e3o Paulo\"}, {\"employer\": \"Ita\u00fa Unibanco\", \"job_title\": \"Data Analyst\", \"start_date\": \"2018\", \"end_date\": \"2021\", \"location\": \"S\u00e3o Paulo\"}], \"education\": [{\"degree\": \"BS Statistics\", \"institution\": \"University of S\u00e3o Paulo (USP)\", \"graduation_year\": \"2018\"}]}"}
{"text": "Liam O'Connor\nliam.oconnor@protonmail.com | +353 87 123 4567 | Dublin, Ireland\n\nEXPERIENCE\n\nSenior Site Reliability Engineer \u2014 Intercom\nJan 2021 \u2013 Present | Dublin, Ireland\n- Managed AWS infrastructure for 500+ microservices using Terraform.\n- Implemented chaos engineering practices, reducing incident resolution time by 30%.\n\nDevOps Engineer \u2014 Workday\nJun 2018 \u2013 Dec 2020 | Dublin, Ireland\n- Built CI/CD pipelines with Jenkins and Groovy, supporting 50+ dev teams.\n- Automated database migrations for PostgreSQL clusters.\n\nEDUCATION\nMSc Cloud Computing \u2014 National College of Ireland \u2014 2018\nBSc Computer Science \u2014 University College Dublin \u2014 2016\n\nSKILLS\nAWS, Terraform, Kubernetes, Python, Go, Bash, Jenkins, Prometheus, ELK Stack, Docker", "output": "{\"personal_information\": {\"name\": \"Liam O'Connor\", \"email\": \"liam.oconnor@protonmail.com\", \"phone\": \"+353 87 123 4567\", \"location\": \"Dublin, Ireland\"}, \"skills\": [\"AWS\", \"Terraform\", \"Kubernetes\", \"Python\", \"Go\", \"Bash\", \"Jenkins\", \"Prometheus\", \"ELK Stack\", \"Docker\"], \"work_experience\": [{\"employer\": \"Intercom\", \"job_title\": \"Senior Site Reliability Engineer\", \"start_date\": \"Jan 2021\", \"end_date\": \"Present\", \"location\": \"Dublin, Ireland\"}, {\"employer\": \"Workday\", \"job_title\": \"DevOps Engineer\", \"start_date\": \"Jun 2018\", \"end_date\": \"Dec 2020\", \"location\": \"Dublin, Ireland\"}], \"education\": [{\"degree\": \"MSc Cloud Computing\", \"institution\": \"National College of Ireland\", \"graduation_year\": \"2018\"}, {\"degree\": \"BSc Computer Science\", \"institution\": \"University College Dublin\", \"graduation_year\": \"2016\"}]}"}
{"text": "HANNAH SCHMIDT\nh.schmidt@email.ch\n+41 79 123 45 67\nZurich, Switzerland\n\nExperience\n\nResearch Engineer \u2014 Google Zurich\nSep 2019 \u2013 Present | Zurich\nWorking on YouTube recommendation algorithms using large-scale deep learning.\nPublished research on bias mitigation in ranking systems at KDD.\n\nSoftware Engineer Intern \u2014 CERN\nJun 2018 \u2013 Aug 2018 | Geneva\nDeveloped data analysis tools for the ATLAS experiment using C++ and ROOT.\n\nEducation\nMSc Computer Science \u2014 ETH Zurich \u2014 2019\nBSc Computer Science \u2014 ETH Zurich \u2014 2017\n\nSkills\nC++, Python, TensorFlow, Flume, MapReduce, Machine Learning, Data Structures, Algorithms", "output": "{\"personal_information\": {\"name\": \"HANNAH SCHMIDT\", \"email\": \"h.schmidt@email.ch\", \"phone\": \"+41 79 123 45 67\", \"location\": \"Zurich, Switzerland\"}, \"skills\": [\"C++\", \"Python\", \"TensorFlow\", \"Flume\", \"MapReduce\", \"Machine Learning\", \"Data Structures\", \"Algorithms\"], \"work_experience\": [{\"employer\": \"Google Zurich\", \"job_title\": \"Research Engineer\", \"start_date\": \"Sep 2019\", \"end_date\": \"Present\", \"location\": \"Zurich\"}, {\"employer\": \"CERN\", \"job_title\": \"Software Engineer Intern\", \"start_date\": \"Jun 2018\", \"end_date\": \"Aug 2018\", \"location\": \"Geneva\"}], \"education\": [{\"degree\": \"MSc Computer Science\", \"institution\": \"ETH Zurich\", \"graduation_year\": \"2019\"}, {\"degree\": \"BSc Computer Science\", \"institution\": \"ETH Zurich\", \"graduation_year\": \"2017\"}]}"}
{"text": "Wei-Hao Chang\nwhchang@mediatek.tw\n+886 912 345 678\nHsinchu, Taiwan\n\nWORK EXPERIENCE\n\nSenior Digital IC Design Engineer \u2014 MediaTek\nJul 2019 \u2013 Present | Hsinchu\n- Designed low-power APU architecture for 5G smartphones.\n- Implemented RTL design using Verilog/SystemVerilog.\n- Conducted synthesis and timing closure (STA) for 5nm process nodes.\n\nFPGA Engineer \u2014 Realtek Semiconductor\nFeb 2016 \u2013 Jun 2019 | Hsinchu\n- Prototyped WiFi MAC layer logic on Xilinx Virtex UltraScale+.\n\nEDUCATION\nM.S. Electronics Engineering \u2014 National Taiwan University \u2014 2016\n\nSKILLS\nVerilog, SystemVerilog, UVM, FPGA, ASIC Design, Synopsys DC, PrimeTime, Python, TCL, C++", "output": "{\"personal_information\": {\"name\": \"Wei-Hao Chang\", \"email\": \"whchang@mediatek.tw\", \"phone\": \"+886 912 345 678\", \"location\": \"Hsinchu, Taiwan\"}, \"skills\": [\"Verilog\", \"SystemVerilog\", \"UVM\", \"FPGA\", \"ASIC Design\", \"Synopsys DC\", \"PrimeTime\", \"Python\", \"TCL\", \"C++\"], \"work_experience\": [{\"employer\": \"MediaTek\", \"job_title\": \"Senior Digital IC Design Engineer\", \"start_date\": \"Jul 2019\", \"end_date\": \"Present\", \"location\": \"Hsinchu\"}, {\"employer\": \"Realtek Semiconductor\", \"job_title\": \"FPGA Engineer\", \"start_date\": \"Feb 2016\", \"end_date\": \"Jun 2019\", \"location\": \"Hsinchu\"}], \"education\": [{\"degree\": \"M.S. Electronics Engineering\", \"institution\": \"National Taiwan University\", \"graduation_year\": \"2016\"}]}"}
{"text": "Lars Svensson\nlars.s@spotify.se | +46 70 123 45 67 | Stockholm, Sweden\n\nExperience\n\nProduct Owner \u2014 Spotify\nAug 2018 \u2013 Present | Stockholm\n- Leading a squad of 8 engineers focused on Discover Weekly personalization.\n- Defined product roadmap and KPIs, increasing weekly active users by 10%.\n- Facilitating Agile ceremonies (Sprint Planning, Retro).\n\nBusiness Analyst \u2014 Klarna\nJun 2015 \u2013 Jul 2018 | Stockholm\n- Analyzed user payment flows to identify friction points.\n\nEducation\nMSc Industrial Engineering \u2014 KTH Royal Institute of Technology \u2014 2015\n\nSkills\nAgile, Scrum, Product Management, Jira, Data Analysis, SQL, Tableau, A/B Testing, User Stories, Stakeholder Management", "output": "{\"personal_information\": {\"name\": \"Lars Svensson\", \"email\": \"lars.s@spotify.se\", \"phone\": \"+46 70 123 45 67\", \"location\": \"Stockholm, Sweden\"}, \"skills\": [\"Agile\", \"Scrum\", \"Product Management\", \"Jira\", \"Data Analysis\", \"SQL\", \"Tableau\", \"A/B Testing\", \"User Stories\", \"Stakeholder Management\"], \"work_experience\": [{\"employer\": \"Spotify\", \"job_title\": \"Product Owner\", \"start_date\": \"Aug 2018\", \"end_date\": \"Present\", \"location\": \"Stockholm\"}, {\"employer\": \"Klarna\", \"job_title\": \"Business Analyst\", \"start_date\": \"Jun 2015\", \"end_date\": \"Jul 2018\", \"location\": \"Stockholm\"}], \"education\": [{\"degree\": \"MSc Industrial Engineering\", \"institution\": \"KTH Royal Institute of Technology\", \"graduation_year\": \"2015\"}]}"}
{"text": "WILLIAM TAYLOR\nwtaylor@tech.net\n(206) 555-9988\nSeattle, WA\n\nEXPERIENCE\n\nPrincipal Software Architect | Microsoft\nNov 2015 \u2013 Present | Redmond, WA\nArchitected Azure AI infrastructure supporting large-scale model training.\nLed technical strategy for a division of 150+ engineers.\n\nSenior Software Engineer | Oracle\nAug 2010 \u2013 Oct 2015 | Seattle, WA\nDesigned high-availability cloud database storage solutions.\nOptimized garbage collection algorithms in custom JVM implementation.\n\nEDUCATION\nPhD Computer Science \u2014 University of Washington \u2014 2010\nMS Computer Science \u2014 University of Washington \u2014 2006\nBS Electrical Engineering \u2014 Purdue University \u2014 2004\n\nSKILLS\nSystem Design, C++, C#, Java, Azure, Cloud Architecture, Distributed Systems, Rust, Kubernetes", "output": "{\"personal_information\": {\"name\": \"WILLIAM TAYLOR\", \"email\": \"wtaylor@tech.net\", \"phone\": \"(206) 555-9988\", \"location\": \"Seattle, WA\"}, \"skills\": [\"System Design\", \"C++\", \"C#\", \"Java\", \"Azure\", \"Cloud Architecture\", \"Distributed Systems\", \"Rust\", \"Kubernetes\"], \"work_experience\": [{\"employer\": \"Microsoft\", \"job_title\": \"Principal Software Architect\", \"start_date\": \"Nov 2015\", \"end_date\": \"Present\", \"location\": \"Redmond, WA\"}, {\"employer\": \"Oracle\", \"job_title\": \"Senior Software Engineer\", \"start_date\": \"Aug 2010\", \"end_date\": \"Oct 2015\", \"location\": \"Seattle, WA\"}], \"education\": [{\"degree\": \"PhD Computer Science\", \"institution\": \"University of Washington\", \"graduation_year\": \"2010\"}, {\"degree\": \"MS Computer Science\", \"institution\": \"University of Washington\", \"graduation_year\": \"2006\"}, {\"degree\": \"BS Electrical Engineering\", \"institution\": \"Purdue University\", \"graduation_year\": \"2004\"}]}"}
{"text": "NINA PETROVA\nnina.petrova@yandex.ru\n+7 999 123-45-67\nMoscow, Russia\n\nEXPERIENCE\n\nComputer Vision Engineer \u2014 Yandex Self-Driving Group\nJun 2020 \u2013 Present | Moscow\nDeveloped 3D object detection models using LiDAR point clouds.\nOptimized inference latency on edge devices using TensorRT.\n\nJunior Data Scientist \u2014 Sberbank\nSep 2018 \u2013 May 2020 | Moscow\nBuilt credit scoring models using XGBoost and LightGBM.\nDeployed models to production using Docker and Flask.\n\nEDUCATION\nMSc Applied Mathematics \u2014 Moscow State University \u2014 2018\nBSc Physics \u2014 Moscow Institute of Physics and Technology \u2014 2016\n\nSKILLS\nPython, C++, PyTorch, TensorFlow, OpenCV, LiDAR, CUDA, Docker, Linux, Git", "output": "{\"personal_information\": {\"name\": \"NINA PETROVA\", \"email\": \"nina.petrova@yandex.ru\", \"phone\": \"+7 999 123-45-67\", \"location\": \"Moscow, Russia\"}, \"skills\": [\"Python\", \"C++\", \"PyTorch\", \"TensorFlow\", \"OpenCV\", \"LiDAR\", \"CUDA\", \"Docker\", \"Linux\", \"Git\"], \"work_experience\": [{\"employer\": \"Yandex Self-Driving Group\", \"job_title\": \"Computer Vision Engineer\", \"start_date\": \"Jun 2020\", \"end_date\": \"Present\", \"location\": \"Moscow\"}, {\"employer\": \"Sberbank\", \"job_title\": \"Junior Data Scientist\", \"start_date\": \"Sep 2018\", \"end_date\": \"May 2020\", \"location\": \"Moscow\"}], \"education\": [{\"degree\": \"MSc Applied Mathematics\", \"institution\": \"Moscow State University\", \"graduation_year\": \"2018\"}, {\"degree\": \"BSc Physics\", \"institution\": \"Moscow Institute of Physics and Technology\", \"graduation_year\": \"2016\"}]}"}
{"text": "Aarav Sharma\naarav.sharma@techmail.in | +91 99887 76655 | Hyderabad, India\n\nPROFESSIONAL SUMMARY\nCybersecurity analyst with 4 years of experience in SOC operations and threat hunting.\n\nEXPERIENCE\nInformation Security Analyst II \u2014 Infosys\nAug 2021 \u2013 Present | Hyderabad\n- Monitored SIEM alerts (Splunk) for 10+ enterprise clients.\n- Conducted vulnerability assessments using Nessus and Qualys.\n- Developed Python scripts to automate threat intelligence feed ingestion.\n\nJunior Security Analyst \u2014 Wipro\nJul 2019 \u2013 Jul 2021 | Bangalore\n- Assisted in incident response for phishing campaigns and malware outbreaks.\n- Configured firewall rules and IDS signatures.\n\nEDUCATION\nB.Tech Information Technology \u2014 JNTU Hyderabad \u2014 2019\n\nSKILLS\nSplunk, Wireshark, Python, Nessus, Metasploit, Linux, TCP/IP, OWASP Top 10, SIEM, Bash", "output": "{\"personal_information\": {\"name\": \"Aarav Sharma\", \"email\": \"aarav.sharma@techmail.in\", \"phone\": \"+91 99887 76655\", \"location\": \"Hyderabad, India\"}, \"skills\": [\"Splunk\", \"Wireshark\", \"Python\", \"Nessus\", \"Metasploit\", \"Linux\", \"TCP/IP\", \"OWASP Top 10\", \"SIEM\", \"Bash\"], \"work_experience\": [{\"employer\": \"Infosys\", \"job_title\": \"Information Security Analyst II\", \"start_date\": \"Aug 2021\", \"end_date\": \"Present\", \"location\": \"Hyderabad\"}, {\"employer\": \"Wipro\", \"job_title\": \"Junior Security Analyst\", \"start_date\": \"Jul 2019\", \"end_date\": \"Jul 2021\", \"location\": \"Bangalore\"}], \"education\": [{\"degree\": \"B.Tech Information Technology\", \"institution\": \"JNTU Hyderabad\", \"graduation_year\": \"2019\"}]}"}
{"text": "Ahmed Hassan\nahmed.hassan@tech.ae | +971 50 123 4567 | Dubai, UAE\n\nProfessional Experience\n\nSenior Systems Engineer \u2014 Emirates Group\nJan 2019 \u2013 Present | Dubai, UAE\n- Managing hybrid cloud infrastructure (Azure + On-premise).\n- Led migration of legacy exchange servers to Office 365.\n- Implemented disaster recovery plans and routine backup testing.\n\nNetwork Administrator \u2014 Etisalat\nMar 2015 \u2013 Dec 2018 | Abu Dhabi, UAE\n- Configured Cisco routers and switches for enterprise clients.\n- Monitored network performance using SolarWinds.\n\nEducation\nBachelor of Computer Engineering \u2014 Khalifa University \u2014 2014\n\nSkills\nWindows Server, Active Directory, Azure, Office 365, Cisco IOS, VMware, PowerShell, Linux, Networking, DNS/DHCP", "output": "{\"personal_information\": {\"name\": \"Ahmed Hassan\", \"email\": \"ahmed.hassan@tech.ae\", \"phone\": \"+971 50 123 4567\", \"location\": \"Dubai, UAE\"}, \"skills\": [\"Windows Server\", \"Active Directory\", \"Azure\", \"Office 365\", \"Cisco IOS\", \"VMware\", \"PowerShell\", \"Linux\", \"Networking\", \"DNS/DHCP\"], \"work_experience\": [{\"employer\": \"Emirates Group\", \"job_title\": \"Senior Systems Engineer\", \"start_date\": \"Jan 2019\", \"end_date\": \"Present\", \"location\": \"Dubai, UAE\"}, {\"employer\": \"Etisalat\", \"job_title\": \"Network Administrator\", \"start_date\": \"Mar 2015\", \"end_date\": \"Dec 2018\", \"location\": \"Abu Dhabi, UAE\"}], \"education\": [{\"degree\": \"Bachelor of Computer Engineering\", \"institution\": \"Khalifa University\", \"graduation_year\": \"2014\"}]}"}
{"text": "JOHN DOE\nNew York, NY\n\nWORK\n\nBloomberg LP (Sep '20 - Current)\nSoftware Engineer. C++ low latency trading systems.\n\nGoldman Sachs (Jul '18 - Aug '20)\nAnalyst. Python/Pandas for risk reporting.\n\nEDU\n\nCornell University\nBS CS, May 2018\n\nSKILLS\nC++, Python, Linux, SQL, Multithreading\n\nCONTACT\njohndoe@email.com\n555-1234", "output": "{\"personal_information\": {\"name\": \"JOHN DOE\", \"email\": \"johndoe@email.com\", \"phone\": \"555-1234\", \"location\": \"New York, NY\"}, \"skills\": [\"C++\", \"Python\", \"Linux\", \"SQL\", \"Multithreading\"], \"work_experience\": [{\"employer\": \"Bloomberg LP\", \"job_title\": \"Software Engineer\", \"start_date\": \"Sep '20\", \"end_date\": \"Current\", \"location\": \"New York, NY\"}, {\"employer\": \"Goldman Sachs\", \"job_title\": \"Analyst\", \"start_date\": \"Jul '18\", \"end_date\": \"Aug '20\", \"location\": \"New York, NY\"}], \"education\": [{\"degree\": \"BS CS\", \"institution\": \"Cornell University\", \"graduation_year\": \"2018\"}]}"}
{"text": "Zhang Wei\nzw.cv@tech.cn\n+86 139 1234 5678\nBeijing, China\n\nProfessional Experience\n\nComputer Vision Researcher \u2014 Megvii (Face++)\nJul 2019 \u2013 Present | Beijing\n- Researching self-supervised learning methods for facial recognition.\n- Published 2 papers at CVPR and ICCV.\n- Deployed models to edge devices using quantization (int8).\n\nAlgorithm Intern \u2014 Baidu\nJan 2018 \u2013 Jun 2019 | Beijing\n- Worked on object detection for autonomous driving datasets.\n\nEducation\nPhD Computer Science \u2014 Tsinghua University \u2014 2019\nBS Automation \u2014 Tsinghua University \u2014 2014\n\nSkills\nPyTorch, TensorFlow, Python, C++, Computer Vision, Deep Learning, OpenCV, Model Quantization, Linux", "output": "{\"personal_information\": {\"name\": \"Zhang Wei\", \"email\": \"zw.cv@tech.cn\", \"phone\": \"+86 139 1234 5678\", \"location\": \"Beijing, China\"}, \"skills\": [\"PyTorch\", \"TensorFlow\", \"Python\", \"C++\", \"Computer Vision\", \"Deep Learning\", \"OpenCV\", \"Model Quantization\", \"Linux\"], \"work_experience\": [{\"employer\": \"Megvii (Face++)\", \"job_title\": \"Computer Vision Researcher\", \"start_date\": \"Jul 2019\", \"end_date\": \"Present\", \"location\": \"Beijing\"}, {\"employer\": \"Baidu\", \"job_title\": \"Algorithm Intern\", \"start_date\": \"Jan 2018\", \"end_date\": \"Jun 2019\", \"location\": \"Beijing\"}], \"education\": [{\"degree\": \"PhD Computer Science\", \"institution\": \"Tsinghua University\", \"graduation_year\": \"2019\"}, {\"degree\": \"BS Automation\", \"institution\": \"Tsinghua University\", \"graduation_year\": \"2014\"}]}"}
{"text": "KLAUS WEBER\nklaus.weber@sap-consult.de\n+49 89 1234 5678\nMunich, Germany\n\nPROFESSIONAL EXPERIENCE\n\nSAP ABAP Consultant \u2014 BMW Group\nOct 2015 \u2013 Present | Munich\n- Developed custom reports and enhancements in SAP MM/SD modules.\n- Migrated custom code for S/4HANA readiness.\n- Integrated SAP with external logistics systems using IDocs and OData.\n\nJunior Developer \u2014 Siemens\nAug 2012 \u2013 Sep 2015 | Nuremberg\n- Support and maintenance of SAP ECC 6.0 systems.\n\nEDUCATION\nDiplom-Informatiker \u2014 Technical University of Munich \u2014 2012\n\nSKILLS\nSAP ABAP, ABAP OO, SAP MM, SAP SD, S/4HANA, IDocs, OData, CDS Views, SQL, German (Native)", "output": "{\"personal_information\": {\"name\": \"KLAUS WEBER\", \"email\": \"klaus.weber@sap-consult.de\", \"phone\": \"+49 89 1234 5678\", \"location\": \"Munich, Germany\"}, \"skills\": [\"SAP ABAP\", \"ABAP OO\", \"SAP MM\", \"SAP SD\", \"S/4HANA\", \"IDocs\", \"OData\", \"CDS Views\", \"SQL\", \"German (Native)\"], \"work_experience\": [{\"employer\": \"BMW Group\", \"job_title\": \"SAP ABAP Consultant\", \"start_date\": \"Oct 2015\", \"end_date\": \"Present\", \"location\": \"Munich\"}, {\"employer\": \"Siemens\", \"job_title\": \"Junior Developer\", \"start_date\": \"Aug 2012\", \"end_date\": \"Sep 2015\", \"location\": \"Nuremberg\"}], \"education\": [{\"degree\": \"Diplom-Informatiker\", \"institution\": \"Technical University of Munich\", \"graduation_year\": \"2012\"}]}"}
{"text": "Ethan Cole\nethan.cole@elixir.dev\n(503) 555-1212\nPortland, OR (Remote)\n\nEXPERIENCE\n\nSenior Backend Engineer \u2014 Discord\nMay 2021 \u2013 Present | Remote\n- Scaling real-time messaging services using Elixir and Phoenix.\n- Optimized Erlang VM (BEAM) tuning for high concurrency.\n\nBackend Developer \u2014 Bleacher Report\nAug 2017 \u2013 Apr 2021 | San Francisco, CA\n- Migrated Ruby on Rails services to Elixir, reducing server costs by 50%.\n\nEDUCATION\nBS Computer Science \u2014 Oregon State University \u2014 2017\n\nSKILLS\nElixir, Phoenix Framework, Erlang/OTP, Ruby on Rails, PostgreSQL, Redis, WebSocket, Docker, Kubernetes, AWS", "output": "{\"personal_information\": {\"name\": \"Ethan Cole\", \"email\": \"ethan.cole@elixir.dev\", \"phone\": \"(503) 555-1212\", \"location\": \"Portland, OR (Remote)\"}, \"skills\": [\"Elixir\", \"Phoenix Framework\", \"Erlang/OTP\", \"Ruby on Rails\", \"PostgreSQL\", \"Redis\", \"WebSocket\", \"Docker\", \"Kubernetes\", \"AWS\"], \"work_experience\": [{\"employer\": \"Discord\", \"job_title\": \"Senior Backend Engineer\", \"start_date\": \"May 2021\", \"end_date\": \"Present\", \"location\": \"Remote\"}, {\"employer\": \"Bleacher Report\", \"job_title\": \"Backend Developer\", \"start_date\": \"Aug 2017\", \"end_date\": \"Apr 2021\", \"location\": \"San Francisco, CA\"}], \"education\": [{\"degree\": \"BS Computer Science\", \"institution\": \"Oregon State University\", \"graduation_year\": \"2017\"}]}"}
{"text": "SEBASTIEN MARTIN\ns.martin@email.fr | +33 7 89 01 23 45 | Lyon, France\n\nEXPERIENCE\n\nSystems Programmer \u2014 Ubisoft\nMar 2020 \u2013 Present | Lyon\n- Developing the Snowdrop engine core systems using C++ and Rust.\n- Integrating Vulkan rendering backend for cross-platform support.\n\nSoftware Engineer \u2014 Thales\nSep 2016 \u2013 Feb 2020 | Paris\n- Worked on safety-critical embedded systems for avionics.\n- Followed DO-178C compliance standards.\n\nEDUCATION\nMaster of Computer Science \u2014 ENS Lyon \u2014 2016\n\nSKILLS\nC++, Rust, Vulkan, OpenGL, Multithreading, Python, CMake, Linux, Embedded Systems, Git", "output": "{\"personal_information\": {\"name\": \"SEBASTIEN MARTIN\", \"email\": \"s.martin@email.fr\", \"phone\": \"+33 7 89 01 23 45\", \"location\": \"Lyon, France\"}, \"skills\": [\"C++\", \"Rust\", \"Vulkan\", \"OpenGL\", \"Multithreading\", \"Python\", \"CMake\", \"Linux\", \"Embedded Systems\", \"Git\"], \"work_experience\": [{\"employer\": \"Ubisoft\", \"job_title\": \"Systems Programmer\", \"start_date\": \"Mar 2020\", \"end_date\": \"Present\", \"location\": \"Lyon\"}, {\"employer\": \"Thales\", \"job_title\": \"Software Engineer\", \"start_date\": \"Sep 2016\", \"end_date\": \"Feb 2020\", \"location\": \"Paris\"}], \"education\": [{\"degree\": \"Master of Computer Science\", \"institution\": \"ENS Lyon\", \"graduation_year\": \"2016\"}]}"}
{"text": "Linda Johnson\nlinda.db@corp.com\n(303) 555-4433\nDenver, CO\n\nWORK EXPERIENCE\n\nSenior Database Administrator \u2014 Dish Network\nApr 2015 \u2013 Present | Denver, CO\n- Managing Oracle Exadata appliances and 500+ databases.\n- Performed database patching, upgrades (12c to 19c), and performance tuning.\n- Implemented Data Guard for high availability.\n\nDBA \u2014 Wells Fargo\nFeb 2010 \u2013 Mar 2015 | Denver, CO\n- Supported mission-critical financial databases.\n\nEDUCATION\nBS Information Systems \u2014 University of Colorado Boulder \u2014 2009\n\nSKILLS\nOracle Database (11g/12c/19c), PL/SQL, RMAN, Data Guard, RAC, GoldenGate, Linux, Shell Scripting, Performance Tuning", "output": "{\"personal_information\": {\"name\": \"Linda Johnson\", \"email\": \"linda.db@corp.com\", \"phone\": \"(303) 555-4433\", \"location\": \"Denver, CO\"}, \"skills\": [\"Oracle Database (11g/12c/19c)\", \"PL/SQL\", \"RMAN\", \"Data Guard\", \"RAC\", \"GoldenGate\", \"Linux\", \"Shell Scripting\", \"Performance Tuning\"], \"work_experience\": [{\"employer\": \"Dish Network\", \"job_title\": \"Senior Database Administrator\", \"start_date\": \"Apr 2015\", \"end_date\": \"Present\", \"location\": \"Denver, CO\"}, {\"employer\": \"Wells Fargo\", \"job_title\": \"DBA\", \"start_date\": \"Feb 2010\", \"end_date\": \"Mar 2015\", \"location\": \"Denver, CO\"}], \"education\": [{\"degree\": \"BS Information Systems\", \"institution\": \"University of Colorado Boulder\", \"graduation_year\": \"2009\"}]}"}
{"text": "Ji-Hoon Park\njpark@tech.kr\n+82 10 9999 8888\nSeongnam, South Korea\n\nExperience\n\nBackend Developer \u2014 Kakao Corp\nFeb 2019 \u2013 Present | Seongnam\n- Migrated Java-based chat server to Kotlin, improving maintainability.\n- Implemented asynchronous event handling using Kafka and Spring Boot.\n\nSoftware Engineer \u2014 Naver Webtoon\nMar 2016 \u2013 Jan 2019 | Seongnam\n- Optimized image delivery API serving millions of users globally.\n\nEducation\nBS Computer Science \u2014 Yonsei University \u2014 2016\n\nSkills\nKotlin, Java, Spring Boot, Kafka, MySQL, Redis, Docker, AWS, JPA/Hibernate, Git", "output": "{\"personal_information\": {\"name\": \"Ji-Hoon Park\", \"email\": \"jpark@tech.kr\", \"phone\": \"+82 10 9999 8888\", \"location\": \"Seongnam, South Korea\"}, \"skills\": [\"Kotlin\", \"Java\", \"Spring Boot\", \"Kafka\", \"MySQL\", \"Redis\", \"Docker\", \"AWS\", \"JPA/Hibernate\", \"Git\"], \"work_experience\": [{\"employer\": \"Kakao Corp\", \"job_title\": \"Backend Developer\", \"start_date\": \"Feb 2019\", \"end_date\": \"Present\", \"location\": \"Seongnam\"}, {\"employer\": \"Naver Webtoon\", \"job_title\": \"Software Engineer\", \"start_date\": \"Mar 2016\", \"end_date\": \"Jan 2019\", \"location\": \"Seongnam\"}], \"education\": [{\"degree\": \"BS Computer Science\", \"institution\": \"Yonsei University\", \"graduation_year\": \"2016\"}]}"}
{"text": "Kevin Patel\nkevin.patel@startup.io | (415) 555-6789 | San Francisco, CA\n\nPROFESSIONAL HISTORY\n\nFounding Engineer \u2014 Stealth Startup\nJan 2023 \u2013 Present | San Francisco, CA\nBuilt MVP for AI-powered legal assistant using OpenAI API and Pinecone.\nSet up initial infrastructure on Vercel and Supabase.\n\nSenior Frontend Engineer \u2014 Coinbase\nFeb 2020 \u2013 Dec 2022 | San Francisco, CA\nDeveloped React Native mobile app features for crypto trading.\nLed accessibility initiatives for web platform.\n\nSoftware Engineer \u2014 Yelp\nAug 2017 \u2013 Jan 2020 | San Francisco, CA\nMaintained business owner dashboard using React and Python.\n\nEDUCATION\nBS Computer Science \u2014 UC San Diego \u2014 2017\n\nSKILLS\nReact, React Native, TypeScript, Node.js, Python, GraphQL, Next.js, Tailwind CSS, PostgreSQL, OpenAI API", "output": "{\"personal_information\": {\"name\": \"Kevin Patel\", \"email\": \"kevin.patel@startup.io\", \"phone\": \"(415) 555-6789\", \"location\": \"San Francisco, CA\"}, \"skills\": [\"React\", \"React Native\", \"TypeScript\", \"Node.js\", \"Python\", \"GraphQL\", \"Next.js\", \"Tailwind CSS\", \"PostgreSQL\", \"OpenAI API\"], \"work_experience\": [{\"employer\": \"Stealth Startup\", \"job_title\": \"Founding Engineer\", \"start_date\": \"Jan 2023\", \"end_date\": \"Present\", \"location\": \"San Francisco, CA\"}, {\"employer\": \"Coinbase\", \"job_title\": \"Senior Frontend Engineer\", \"start_date\": \"Feb 2020\", \"end_date\": \"Dec 2022\", \"location\": \"San Francisco, CA\"}, {\"employer\": \"Yelp\", \"job_title\": \"Software Engineer\", \"start_date\": \"Aug 2017\", \"end_date\": \"Jan 2020\", \"location\": \"San Francisco, CA\"}], \"education\": [{\"degree\": \"BS Computer Science\", \"institution\": \"UC San Diego\", \"graduation_year\": \"2017\"}]}"}
{"text": "Chloe Dubois\nParis, France\nchloe.d@email.fr\n\nExperience\n\nData Scientist at Carrefour (Massy)\nSince Feb 2020\n\nData Analyst at Orange (Paris)\nSept 2017 to Jan 2020\n\nEducation\nEcole Polytechnique (2017)\nMaster Data Science\n\nSkills\nPython; R; SQL; TensorFlow; Keras; Tableau; Spark", "output": "{\"personal_information\": {\"name\": \"Chloe Dubois\", \"email\": \"chloe.d@email.fr\", \"phone\": \"\", \"location\": \"Paris, France\"}, \"skills\": [\"Python\", \"R\", \"SQL\", \"TensorFlow\", \"Keras\", \"Tableau\", \"Spark\"], \"work_experience\": [{\"employer\": \"Carrefour\", \"job_title\": \"Data Scientist\", \"start_date\": \"Feb 2020\", \"end_date\": \"Present\", \"location\": \"Massy\"}, {\"employer\": \"Orange\", \"job_title\": \"Data Analyst\", \"start_date\": \"Sept 2017\", \"end_date\": \"Jan 2020\", \"location\": \"Paris\"}], \"education\": [{\"degree\": \"Master Data Science\", \"institution\": \"Ecole Polytechnique\", \"graduation_year\": \"2017\"}]}"}
{"text": "Ravi Kumar\nravi.snow@hcl.com | +91 98440 55667 | Bangalore, India\n\nSummary\nServiceNow Certified Implementation Specialist with 5 years experience.\n\nExperience\n\nServiceNow Developer \u2014 HCL Technologies\nJul 2019 \u2013 Present | Bangalore\n- Configuring ITSM and ITOM modules for global clients.\n- Developing custom workflows and catalog items.\n- Scripting business rules and client scripts using JavaScript.\n\nSystem Administrator \u2014 Wipro\nMay 2017 \u2013 Jun 2019 | Bangalore\n- L2 support for ServiceNow ticketing system.\n\nEducation\nB.Tech Electronics \u2014 VTU \u2014 2017\n\nSkills\nServiceNow, ITSM, ITOM, JavaScript, Glide API, CMDB, Workflow Editor, HTML/CSS, REST API Integration", "output": "{\"personal_information\": {\"name\": \"Ravi Kumar\", \"email\": \"ravi.snow@hcl.com\", \"phone\": \"+91 98440 55667\", \"location\": \"Bangalore, India\"}, \"skills\": [\"ServiceNow\", \"ITSM\", \"ITOM\", \"JavaScript\", \"Glide API\", \"CMDB\", \"Workflow Editor\", \"HTML/CSS\", \"REST API Integration\"], \"work_experience\": [{\"employer\": \"HCL Technologies\", \"job_title\": \"ServiceNow Developer\", \"start_date\": \"Jul 2019\", \"end_date\": \"Present\", \"location\": \"Bangalore\"}, {\"employer\": \"Wipro\", \"job_title\": \"System Administrator\", \"start_date\": \"May 2017\", \"end_date\": \"Jun 2019\", \"location\": \"Bangalore\"}], \"education\": [{\"degree\": \"B.Tech Electronics\", \"institution\": \"VTU\", \"graduation_year\": \"2017\"}]}"}
{"text": "RESUME\n\nName: Akira Tanaka\nAddr: Tokyo, Japan\nPh: +81 90 5555 1234\nMail: akira.t@sony.jp\n\n-- SKILL SET --\nC++, Embedded Linux, RTOS, Qt, OpenCV, Git, Bash\n\n-- CAREER --\n\n> Sony Corp (Tokyo)\n> Firmware Engineer\n> Apr 2015 ... Current\n> Developing camera ISP firmware.\n\n> Panasonic (Osaka)\n> Embedded Eng.\n> Apr 2012 ... Mar 2015\n> Worked on smart TV SoC.\n\n-- ACADEMIC --\nMaster Eng. - Kyoto Univ (2012)", "output": "{\"personal_information\": {\"name\": \"Akira Tanaka\", \"email\": \"akira.t@sony.jp\", \"phone\": \"+81 90 5555 1234\", \"location\": \"Tokyo, Japan\"}, \"skills\": [\"C++\", \"Embedded Linux\", \"RTOS\", \"Qt\", \"OpenCV\", \"Git\", \"Bash\"], \"work_experience\": [{\"employer\": \"Sony Corp\", \"job_title\": \"Firmware Engineer\", \"start_date\": \"Apr 2015\", \"end_date\": \"Current\", \"location\": \"Tokyo\"}, {\"employer\": \"Panasonic\", \"job_title\": \"Embedded Eng.\", \"start_date\": \"Apr 2012\", \"end_date\": \"Mar 2015\", \"location\": \"Osaka\"}], \"education\": [{\"degree\": \"Master Eng.\", \"institution\": \"Kyoto Univ\", \"graduation_year\": \"2012\"}]}"}
{"text": "NAME: Samuel Kim\nROLE: Frontend Engineer\nLOC: Seoul, South Korea\nEMAIL: sam.kim@naver.com\n\nSKILLS: JavaScript (ES6+), React, TypeScript, Next.js, CSS-in-JS, Webpack.\n\nEXPERIENCE:\n\n* Coupang (Seoul) -- Frontend Lead\n  May 2020 - Present\n\n* Samsung SDS (Seoul) -- Web Developer\n  Mar 2016 - Apr 2020\n\nEDUCATION:\nKAIST, BS Computer Science (2016)", "output": "{\"personal_information\": {\"name\": \"Samuel Kim\", \"email\": \"sam.kim@naver.com\", \"phone\": \"\", \"location\": \"Seoul, South Korea\"}, \"skills\": [\"JavaScript (ES6+)\", \"React\", \"TypeScript\", \"Next.js\", \"CSS-in-JS\", \"Webpack\"], \"work_experience\": [{\"employer\": \"Coupang\", \"job_title\": \"Frontend Lead\", \"start_date\": \"May 2020\", \"end_date\": \"Present\", \"location\": \"Seoul\"}, {\"employer\": \"Samsung SDS\", \"job_title\": \"Web Developer\", \"start_date\": \"Mar 2016\", \"end_date\": \"Apr 2020\", \"location\": \"Seoul\"}], \"education\": [{\"degree\": \"BS Computer Science\", \"institution\": \"KAIST\", \"graduation_year\": \"2016\"}]}"}
{"text": "TECHNICAL SKILLS: Python; Django; React; AWS (EC2, S3); Docker; Linux/Unix\n\nEXPERIENCE\n\nSoftware Engineer II\nDropbox - San Francisco, CA\n(Aug 2019 - Present)\n* Optimized file sync engine.\n* Mentored juniors.\n\nSoftware Engineer\nOracle (Redwood City)\nJune 2016 to July 2019\n* Java backend development for cloud ERP.\n\nEDUCATION\n\nUniv of California, Berkeley\nB.A. Computer Science, 2016\n\nCONTACT\nJames 'Jim' Halpert\njim.halpert@dundermifflin.com\n(415) 555-0199", "output": "{\"personal_information\": {\"name\": \"James 'Jim' Halpert\", \"email\": \"jim.halpert@dundermifflin.com\", \"phone\": \"(415) 555-0199\", \"location\": \"San Francisco, CA\"}, \"skills\": [\"Python\", \"Django\", \"React\", \"AWS (EC2, S3)\", \"Docker\", \"Linux/Unix\"], \"work_experience\": [{\"employer\": \"Dropbox\", \"job_title\": \"Software Engineer II\", \"start_date\": \"Aug 2019\", \"end_date\": \"Present\", \"location\": \"San Francisco, CA\"}, {\"employer\": \"Oracle\", \"job_title\": \"Software Engineer\", \"start_date\": \"June 2016\", \"end_date\": \"July 2019\", \"location\": \"Redwood City\"}], \"education\": [{\"degree\": \"B.A. Computer Science\", \"institution\": \"Univ of California, Berkeley\", \"graduation_year\": \"2016\"}]}"}
{"text": "Robert Brown\nrobert.b@consulting.com | (312) 555-7777 | Chicago, IL\n\nWork Experience\n\nSolutions Architect \u2014 AWS | Apr 2022 \u2013 Present | Chicago, IL\nDesigned cloud-native architectures for Fortune 100 clients.\nFacilitated workshops on serverless computing and containerization strategies.\n\nIT Consultant \u2014 Accenture | Sep 2018 \u2013 Mar 2022 | Chicago, IL\nLed digital transformation projects for manufacturing clients.\nImplemented SAP S/4HANA migration strategies.\n\nEducation\nMBA \u2014 University of Chicago Booth School of Business \u2014 2018\nBS Information Systems \u2014 University of Illinois Urbana-Champaign \u2014 2013\n\nSkills\nCloud Strategy, AWS, Azure, Enterprise Architecture, SAP, Agile, Scrum, Project Management, Python", "output": "{\"personal_information\": {\"name\": \"Robert Brown\", \"email\": \"robert.b@consulting.com\", \"phone\": \"(312) 555-7777\", \"location\": \"Chicago, IL\"}, \"skills\": [\"Cloud Strategy\", \"AWS\", \"Azure\", \"Enterprise Architecture\", \"SAP\", \"Agile\", \"Scrum\", \"Project Management\", \"Python\"], \"work_experience\": [{\"employer\": \"AWS\", \"job_title\": \"Solutions Architect\", \"start_date\": \"Apr 2022\", \"end_date\": \"Present\", \"location\": \"Chicago, IL\"}, {\"employer\": \"Accenture\", \"job_title\": \"IT Consultant\", \"start_date\": \"Sep 2018\", \"end_date\": \"Mar 2022\", \"location\": \"Chicago, IL\"}], \"education\": [{\"degree\": \"MBA\", \"institution\": \"University of Chicago Booth School of Business\", \"graduation_year\": \"2018\"}, {\"degree\": \"BS Information Systems\", \"institution\": \"University of Illinois Urbana-Champaign\", \"graduation_year\": \"2013\"}]}"}
{"text": "Ahmed Khalid\nCairo, Egypt\n+20 100 123 4567\nahmed.k@dev.eg\n\nEXPERIENCE\n\nVodafone Egypt (Cairo)\nNetwork Engineer\nJun 2016 - Present\n\nOrange Egypt (Cairo)\nJunior Support Eng\nJan 2014 - May 2016\n\nEDUCATION\nCairo University\nBSc Telecommunications (2013)\n\nSKILLS\nCCNA, CCNP, Cisco IOS, MPLS, BGP, Python, Linux", "output": "{\"personal_information\": {\"name\": \"Ahmed Khalid\", \"email\": \"ahmed.k@dev.eg\", \"phone\": \"+20 100 123 4567\", \"location\": \"Cairo, Egypt\"}, \"skills\": [\"CCNA\", \"CCNP\", \"Cisco IOS\", \"MPLS\", \"BGP\", \"Python\", \"Linux\"], \"work_experience\": [{\"employer\": \"Vodafone Egypt\", \"job_title\": \"Network Engineer\", \"start_date\": \"Jun 2016\", \"end_date\": \"Present\", \"location\": \"Cairo\"}, {\"employer\": \"Orange Egypt\", \"job_title\": \"Junior Support Eng\", \"start_date\": \"Jan 2014\", \"end_date\": \"May 2016\", \"location\": \"Cairo\"}], \"education\": [{\"degree\": \"BSc Telecommunications\", \"institution\": \"Cairo University\", \"graduation_year\": \"2013\"}]}"}
{"text": "Ciaran Murphy\ncmurphy@docs.ie | +353 86 000 0000 | Cork, Ireland\n\nProfile\nSenior Technical Writer with 8 years experience in API documentation and developer portals.\n\nExperience\n\nStaff Technical Writer \u2014 Stripe\nMar 2020 \u2013 Present | Remote (Ireland)\n- Authored comprehensive integration guides for Stripe Connect.\n- Maintained OpenAPI specifications using Stoplight.\n- Edited engineering blog posts for technical accuracy.\n\nTechnical Writer \u2014 Red Hat\nJan 2016 \u2013 Feb 2020 | Cork\n- Wrote installation and administration guides for Red Hat Enterprise Linux.\n\nEducation\nMA Technical Communication \u2014 University of Limerick \u2014 2015\nBA English \u2014 University College Cork \u2014 2013\n\nSkills\nMarkdown, XML/DITA, Git, REST APIs, OpenAPI/Swagger, Static Site Generators (Hugo/Jekyll), Linux, HTML/CSS", "output": "{\"personal_information\": {\"name\": \"Ciaran Murphy\", \"email\": \"cmurphy@docs.ie\", \"phone\": \"+353 86 000 0000\", \"location\": \"Cork, Ireland\"}, \"skills\": [\"Markdown\", \"XML/DITA\", \"Git\", \"REST APIs\", \"OpenAPI/Swagger\", \"Static Site Generators (Hugo/Jekyll)\", \"Linux\", \"HTML/CSS\"], \"work_experience\": [{\"employer\": \"Stripe\", \"job_title\": \"Staff Technical Writer\", \"start_date\": \"Mar 2020\", \"end_date\": \"Present\", \"location\": \"Remote (Ireland)\"}, {\"employer\": \"Red Hat\", \"job_title\": \"Technical Writer\", \"start_date\": \"Jan 2016\", \"end_date\": \"Feb 2020\", \"location\": \"Cork\"}], \"education\": [{\"degree\": \"MA Technical Communication\", \"institution\": \"University of Limerick\", \"graduation_year\": \"2015\"}, {\"degree\": \"BA English\", \"institution\": \"University College Cork\", \"graduation_year\": \"2013\"}]}"}
{"text": "CARLOS GOMEZ\ncarlos.gomez@webmail.es\n+34 600 111 222\nMadrid, Spain\n\nWORK HISTORY\n\nFrontend Developer \u2014 Cabify\nFeb 2020 \u2013 Present | Madrid\n- Building internal back-office tools using Vue.js and Nuxt.js.\n- Implemented state management using Pinia (formerly Vuex).\n- Integrated map visualization libraries (Leaflet).\n\nWeb Developer \u2014 Indra\nSep 2017 \u2013 Jan 2020 | Madrid\n- Developed responsive websites for public sector clients using HTML/CSS/JS.\n\nEDUCATION\nGrado en Ingenier\u00eda Inform\u00e1tica \u2014 Universidad Polit\u00e9cnica de Madrid \u2014 2017\n\nSKILLS\nJavaScript, Vue.js, Nuxt.js, HTML5, CSS3, Pinia, Vuex, Tailwind CSS, Git, Jest", "output": "{\"personal_information\": {\"name\": \"CARLOS GOMEZ\", \"email\": \"carlos.gomez@webmail.es\", \"phone\": \"+34 600 111 222\", \"location\": \"Madrid, Spain\"}, \"skills\": [\"JavaScript\", \"Vue.js\", \"Nuxt.js\", \"HTML5\", \"CSS3\", \"Pinia\", \"Vuex\", \"Tailwind CSS\", \"Git\", \"Jest\"], \"work_experience\": [{\"employer\": \"Cabify\", \"job_title\": \"Frontend Developer\", \"start_date\": \"Feb 2020\", \"end_date\": \"Present\", \"location\": \"Madrid\"}, {\"employer\": \"Indra\", \"job_title\": \"Web Developer\", \"start_date\": \"Sep 2017\", \"end_date\": \"Jan 2020\", \"location\": \"Madrid\"}], \"education\": [{\"degree\": \"Grado en Ingenier\u00eda Inform\u00e1tica\", \"institution\": \"Universidad Polit\u00e9cnica de Madrid\", \"graduation_year\": \"2017\"}]}"}
{"text": "Lucas Silva\nlucas.silva@uol.com.br | (11) 91234-5678 | S\u00e3o Paulo, Brazil\n\nProfessional Experience\n\nSenior Android Engineer \u2014 Nubank | Oct 2020 \u2013 Present | S\u00e3o Paulo\nArchitected modularized banking app features using Kotlin and Clean Architecture.\nReduced APK size by 40% through ProGuard optimization and dynamic feature delivery.\n\nAndroid Developer \u2014 Mercado Libre | Aug 2017 \u2013 Sep 2020 | S\u00e3o Paulo\nImplemented payment flows using NFC and biometric authentication.\nMaintained 99.9% crash-free sessions for 10M+ users.\n\nEducation\nBS Computer Science \u2014 University of S\u00e3o Paulo (USP) \u2014 2017\n\nTechnical Skills\nKotlin, Java, Jetpack Compose, RxJava, Dagger/Hilt, Coroutines, Retrofit, JUnit, Espresso, Git", "output": "{\"personal_information\": {\"name\": \"Lucas Silva\", \"email\": \"lucas.silva@uol.com.br\", \"phone\": \"(11) 91234-5678\", \"location\": \"S\u00e3o Paulo, Brazil\"}, \"skills\": [\"Kotlin\", \"Java\", \"Jetpack Compose\", \"RxJava\", \"Dagger/Hilt\", \"Coroutines\", \"Retrofit\", \"JUnit\", \"Espresso\", \"Git\"], \"work_experience\": [{\"employer\": \"Nubank\", \"job_title\": \"Senior Android Engineer\", \"start_date\": \"Oct 2020\", \"end_date\": \"Present\", \"location\": \"S\u00e3o Paulo\"}, {\"employer\": \"Mercado Libre\", \"job_title\": \"Android Developer\", \"start_date\": \"Aug 2017\", \"end_date\": \"Sep 2020\", \"location\": \"S\u00e3o Paulo\"}], \"education\": [{\"degree\": \"BS Computer Science\", \"institution\": \"University of S\u00e3o Paulo (USP)\", \"graduation_year\": \"2017\"}]}"}
{"text": "Chen Wei - Full Stack Dev\nBeijing, China | +86 138 0000 0000 | cw@qq.com\n\nSkills: Vue.js, Node.js, MySQL, Redis, AliCloud, Docker.\n\nByteDance (2020-Present): Backend Engineer. Douyin Core Team.\nTencent (2017-2020): Frontend Dev. WeChat Mini Programs.\n\nEducation: Tsinghua Univ, Master of Software Eng (2017).", "output": "{\"personal_information\": {\"name\": \"Chen Wei\", \"email\": \"cw@qq.com\", \"phone\": \"+86 138 0000 0000\", \"location\": \"Beijing, China\"}, \"skills\": [\"Vue.js\", \"Node.js\", \"MySQL\", \"Redis\", \"AliCloud\", \"Docker\"], \"work_experience\": [{\"employer\": \"ByteDance\", \"job_title\": \"Backend Engineer\", \"start_date\": \"2020\", \"end_date\": \"Present\", \"location\": \"Beijing\"}, {\"employer\": \"Tencent\", \"job_title\": \"Frontend Dev\", \"start_date\": \"2017\", \"end_date\": \"2020\", \"location\": \"Beijing\"}], \"education\": [{\"degree\": \"Master of Software Eng\", \"institution\": \"Tsinghua Univ\", \"graduation_year\": \"2017\"}]}"}
{"text": "Rahul Gupta\nBangalore, India\n\nTech Stack: React Native, Redux, TypeScript, Firebase, Jest.\n\nEmployment History:\n- Mobile Lead @ Swiggy (Aug '21 - Present)\n- Senior Android Dev @ Ola Cabs (July '18 - July '21)\n\nEducation:\nB.Tech CSE, VIT Vellore (2018)\n\nEmail: rahul.g@tech.in\nPhone: +91 99999 88888", "output": "{\"personal_information\": {\"name\": \"Rahul Gupta\", \"email\": \"rahul.g@tech.in\", \"phone\": \"+91 99999 88888\", \"location\": \"Bangalore, India\"}, \"skills\": [\"React Native\", \"Redux\", \"TypeScript\", \"Firebase\", \"Jest\"], \"work_experience\": [{\"employer\": \"Swiggy\", \"job_title\": \"Mobile Lead\", \"start_date\": \"Aug '21\", \"end_date\": \"Present\", \"location\": \"Bangalore\"}, {\"employer\": \"Ola Cabs\", \"job_title\": \"Senior Android Dev\", \"start_date\": \"July '18\", \"end_date\": \"July '21\", \"location\": \"Bangalore\"}], \"education\": [{\"degree\": \"B.Tech CSE\", \"institution\": \"VIT Vellore\", \"graduation_year\": \"2018\"}]}"}
{"text": "SOPHIA CHEN\nsophia.c@gmail.com\n(604) 555-0199\nVancouver, BC, Canada\n\nWORK HISTORY\n\nLead iOS Developer | Slack | Feb 2020 \u2013 Present | Vancouver, BC\nLed the rewrite of the mobile message rendering engine in Swift, improving scroll performance by 60fps.\nMentored 4 junior iOS engineers and established code review guidelines.\n\niOS Developer | Hootsuite | May 2017 \u2013 Jan 2020 | Vancouver, BC\nIntegrated dark mode support across the entire iOS application.\nReduced app launch time by 2s through dynamic framework optimization.\n\nEDUCATION\nBSc Software Engineering\nUniversity of British Columbia\n2017\n\nSKILLS\nSwift, Objective-C, SwiftUI, UIKit, CocoaPods, Fastlane, XCTest, Jenkins, GraphQL, Git", "output": "{\"personal_information\": {\"name\": \"SOPHIA CHEN\", \"email\": \"sophia.c@gmail.com\", \"phone\": \"(604) 555-0199\", \"location\": \"Vancouver, BC, Canada\"}, \"skills\": [\"Swift\", \"Objective-C\", \"SwiftUI\", \"UIKit\", \"CocoaPods\", \"Fastlane\", \"XCTest\", \"Jenkins\", \"GraphQL\", \"Git\"], \"work_experience\": [{\"employer\": \"Slack\", \"job_title\": \"Lead iOS Developer\", \"start_date\": \"Feb 2020\", \"end_date\": \"Present\", \"location\": \"Vancouver, BC\"}, {\"employer\": \"Hootsuite\", \"job_title\": \"iOS Developer\", \"start_date\": \"May 2017\", \"end_date\": \"Jan 2020\", \"location\": \"Vancouver, BC\"}], \"education\": [{\"degree\": \"BSc Software Engineering\", \"institution\": \"University of British Columbia\", \"graduation_year\": \"2017\"}]}"}
{"text": "Sarah Jenkins\nsarah.jenkins@security.com\n(703) 555-9876\nWashington, DC\n\nEXPERIENCE\n\nChief Information Security Officer (CISO) \u2014 Booz Allen Hamilton\nJan 2018 \u2013 Present | Washington, DC\n- Defining enterprise security strategy for federal contracts.\n- Managing a team of 50+ security professionals.\n- Overseeing compliance with NIST 800-53 and FISMA.\n\nDirector of Security \u2014 Northrop Grumman\nJun 2010 \u2013 Dec 2017 | Falls Church, VA\n- Led incident response for APT attacks.\n\nEDUCATION\nMS Cybersecurity \u2014 Johns Hopkins University \u2014 2010\nBS Computer Science \u2014 University of Maryland \u2014 2005\n\nSKILLS\nInformation Security Strategy, Risk Management, NIST Framework, FISMA, Leadership, Incident Response, Compliance, CISSP, CISM", "output": "{\"personal_information\": {\"name\": \"Sarah Jenkins\", \"email\": \"sarah.jenkins@security.com\", \"phone\": \"(703) 555-9876\", \"location\": \"Washington, DC\"}, \"skills\": [\"Information Security Strategy\", \"Risk Management\", \"NIST Framework\", \"FISMA\", \"Leadership\", \"Incident Response\", \"Compliance\", \"CISSP\", \"CISM\"], \"work_experience\": [{\"employer\": \"Booz Allen Hamilton\", \"job_title\": \"Chief Information Security Officer (CISO)\", \"start_date\": \"Jan 2018\", \"end_date\": \"Present\", \"location\": \"Washington, DC\"}, {\"employer\": \"Northrop Grumman\", \"job_title\": \"Director of Security\", \"start_date\": \"Jun 2010\", \"end_date\": \"Dec 2017\", \"location\": \"Falls Church, VA\"}], \"education\": [{\"degree\": \"MS Cybersecurity\", \"institution\": \"Johns Hopkins University\", \"graduation_year\": \"2010\"}, {\"degree\": \"BS Computer Science\", \"institution\": \"University of Maryland\", \"graduation_year\": \"2005\"}]}"}
{"text": "DevOps / SRE Resume\n\nNAME: Tom Wilson\nLOC: Seattle, WA\nCONTACT: tom.w@cloud.net\n\n-- TECH --\nAWS, Azure, Terraform, Ansible, Jenkins, Python, Bash, Docker.\n\n-- JOBS --\n\n2021-Now: Senior DevOps Eng @ Microsoft (Redmond)\n2018-2021: Cloud Engineer @ Amazon (Seattle)\n\n-- SCHOOL --\nUniv of Washington (2018) - BS Comp Sci.", "output": "{\"personal_information\": {\"name\": \"Tom Wilson\", \"email\": \"tom.w@cloud.net\", \"phone\": \"\", \"location\": \"Seattle, WA\"}, \"skills\": [\"AWS\", \"Azure\", \"Terraform\", \"Ansible\", \"Jenkins\", \"Python\", \"Bash\", \"Docker\"], \"work_experience\": [{\"employer\": \"Microsoft\", \"job_title\": \"Senior DevOps Eng\", \"start_date\": \"2021\", \"end_date\": \"Now\", \"location\": \"Redmond\"}, {\"employer\": \"Amazon\", \"job_title\": \"Cloud Engineer\", \"start_date\": \"2018\", \"end_date\": \"2021\", \"location\": \"Seattle\"}], \"education\": [{\"degree\": \"BS Comp Sci\", \"institution\": \"Univ of Washington\", \"graduation_year\": \"2018\"}]}"}
{"text": "Gary Davis\ngdavis@legacy.net\n(804) 555-8899\nRichmond, VA\n\nSUMMARY\nMainframe Developer with 20+ years of experience in the banking sector.\n\nEXPERIENCE\n\nSystems Analyst \u2014 Capital One\nAug 2005 \u2013 Present | Richmond, VA\n- Maintenance and enhancement of core banking systems in COBOL.\n- Managing batch processing jobs using JCL and CICS transaction processing.\n- Assisted in legacy modernization initiatives to AWS.\n\nProgrammer Analyst \u2014 Bank of America\nMay 1998 \u2013 Jul 2005 | Charlotte, NC\n- Developed DB2 stored procedures for credit card processing.\n\nEDUCATION\nBS Computer Science \u2014 Virginia Tech \u2014 1998\n\nSKILLS\nCOBOL, JCL, CICS, DB2, VSAM, z/OS, IBM Mainframe, SQL, Endevor, TSO/ISPF", "output": "{\"personal_information\": {\"name\": \"Gary Davis\", \"email\": \"gdavis@legacy.net\", \"phone\": \"(804) 555-8899\", \"location\": \"Richmond, VA\"}, \"skills\": [\"COBOL\", \"JCL\", \"CICS\", \"DB2\", \"VSAM\", \"z/OS\", \"IBM Mainframe\", \"SQL\", \"Endevor\", \"TSO/ISPF\"], \"work_experience\": [{\"employer\": \"Capital One\", \"job_title\": \"Systems Analyst\", \"start_date\": \"Aug 2005\", \"end_date\": \"Present\", \"location\": \"Richmond, VA\"}, {\"employer\": \"Bank of America\", \"job_title\": \"Programmer Analyst\", \"start_date\": \"May 1998\", \"end_date\": \"Jul 2005\", \"location\": \"Charlotte, NC\"}], \"education\": [{\"degree\": \"BS Computer Science\", \"institution\": \"Virginia Tech\", \"graduation_year\": \"1998\"}]}"}
{"text": "ELENA ROSSI\nelena.rossi@email.it\n+39 333 1234567\nMilan, Italy\n\nExperience\n\nProduct Designer \u2014 YOOX NET-A-PORTER GROUP\nMar 2019 \u2013 Present | Milan, Italy\nDesigned end-to-end checkout flow for mobile app, increasing conversion by 12%.\nCreated comprehensive design system used by 30+ designers and developers.\n\nUX/UI Designer \u2014 Reply\nJan 2017 \u2013 Feb 2019 | Turin, Italy\nConducted user research and usability testing for banking clients.\nPrototyped interactive interfaces using Figma and Principle.\n\nEducation\nMA Interaction Design \u2014 Domus Academy \u2014 2016\nBA Graphic Design \u2014 Politecnico di Milano \u2014 2015\n\nSkills\nFigma, Sketch, Adobe XD, Principle, HTML, CSS, User Research, Prototyping, Wireframing", "output": "{\"personal_information\": {\"name\": \"ELENA ROSSI\", \"email\": \"elena.rossi@email.it\", \"phone\": \"+39 333 1234567\", \"location\": \"Milan, Italy\"}, \"skills\": [\"Figma\", \"Sketch\", \"Adobe XD\", \"Principle\", \"HTML\", \"CSS\", \"User Research\", \"Prototyping\", \"Wireframing\"], \"work_experience\": [{\"employer\": \"YOOX NET-A-PORTER GROUP\", \"job_title\": \"Product Designer\", \"start_date\": \"Mar 2019\", \"end_date\": \"Present\", \"location\": \"Milan, Italy\"}, {\"employer\": \"Reply\", \"job_title\": \"UX/UI Designer\", \"start_date\": \"Jan 2017\", \"end_date\": \"Feb 2019\", \"location\": \"Turin, Italy\"}], \"education\": [{\"degree\": \"MA Interaction Design\", \"institution\": \"Domus Academy\", \"graduation_year\": \"2016\"}, {\"degree\": \"BA Graphic Design\", \"institution\": \"Politecnico di Milano\", \"graduation_year\": \"2015\"}]}"}
{"text": "Maria Rodriguez\nmrod@vrstudio.ca\n(514) 555-9090\nMontreal, QC, Canada\n\nWORK HISTORY\n\nAR/VR Developer \u2014 Unity Technologies\nJun 2021 \u2013 Present | Montreal\n- Building interaction toolkits for Unity XR framework.\n- Prototyping hand-tracking gestures for Oculus Quest 2.\n\nUnity Developer \u2014 Ludia\nMay 2018 \u2013 May 2021 | Montreal\n- Optimized shader performance for mobile AR games.\n- Integrated Niantic Lightship ARDK.\n\nEDUCATION\nB.Fine Arts (Computation Arts) \u2014 Concordia University \u2014 2018\n\nSKILLS\nC#, Unity 3D, XR Interaction Toolkit, HLSL/GLSL, ARCore, ARKit, Oculus SDK, Git, Blender", "output": "{\"personal_information\": {\"name\": \"Maria Rodriguez\", \"email\": \"mrod@vrstudio.ca\", \"phone\": \"(514) 555-9090\", \"location\": \"Montreal, QC, Canada\"}, \"skills\": [\"C#\", \"Unity 3D\", \"XR Interaction Toolkit\", \"HLSL/GLSL\", \"ARCore\", \"ARKit\", \"Oculus SDK\", \"Git\", \"Blender\"], \"work_experience\": [{\"employer\": \"Unity Technologies\", \"job_title\": \"AR/VR Developer\", \"start_date\": \"Jun 2021\", \"end_date\": \"Present\", \"location\": \"Montreal\"}, {\"employer\": \"Ludia\", \"job_title\": \"Unity Developer\", \"start_date\": \"May 2018\", \"end_date\": \"May 2021\", \"location\": \"Montreal\"}], \"education\": [{\"degree\": \"B.Fine Arts (Computation Arts)\", \"institution\": \"Concordia University\", \"graduation_year\": \"2018\"}]}"}